{
  "SJML": {
    "header": {
      "identifier": "텍스트_구어체 말뭉치 구축_0001660018",
      "name": "컨테이너 텍스트 인식을 위한 학습용 데이터셋",
      "type": "0",
      "source_file": "BOBR210001660018"
    },
    "text": [
      {
        "content": "에고 애기들 너무 귀엽다",
        "writer": "Ugzfcaz3k2YI_PFzE554AaABAg",
        "write_date": "2021-10-28",
        "url": "https://www.youtube.com/channel/UCK1sVuXaDvJeNwl9noN5nOA",
        "parent_url": "https://www.youtube.com/watch?v=ZnmqK4NPIro",
        "source_site": "https://www.youtube.com/"
      },
      {
        "content": "얘들 제발 그만나와라. 애들팔아 돈벌어 먹냐",
        "writer": "Ugxm_WxPmk_qI-5Wv5t4AaABAg",
        "write_date": "2021-07-18",
        "url": "https://www.youtube.com/channel/UCK1sVuXaDvJeNwl9noN5nOA",
        "parent_url": "https://www.youtube.com/watch?v=ZnmqK4NPIro",
        "source_site": "https://www.youtube.com/"
      },
      {
        "content": "울하영이 넘무귀여워 멋진연우 오빠 든든해 어쩜저리귀여울까",
        "writer": "Ugzrzi8NZUgaJD6XJKB4AaABAg",
        "write_date": "2021-07-18",
        "url": "https://www.youtube.com/channel/UCK1sVuXaDvJeNwl9noN5nOA",
        "parent_url": "https://www.youtube.com/watch?v=ZnmqK4NPIro",
        "source_site": "https://www.youtube.com/"
      },
      {
        "content": "어쩜이리 똑똑하지",
        "writer": "UgxCflFRugS9CGUqHE54AaABAg",
        "write_date": "2021-06-18",
        "url": "https://www.youtube.com/channel/UCK1sVuXaDvJeNwl9noN5nOA",
        "parent_url": "https://www.youtube.com/watch?v=ZnmqK4NPIro",
        "source_site": "https://www.youtube.com/"
      },
      {
        "content": "오래동안지켜봐도 어떻게 26개월짜리이렇게 정확히판단하고 표현하는가요와 뚀하영 예술입니다",
        "writer": "UgzyoSuAGgDz_5lfl454AaABAg",
        "write_date": "2021-06-18",
        "url": "https://www.youtube.com/channel/UCK1sVuXaDvJeNwl9noN5nOA",
        "parent_url": "https://www.youtube.com/watch?v=ZnmqK4NPIro",
        "source_site": "https://www.youtube.com/"
      },
      {
        "content": "거침없이 상황판단한대로 꾸밈없이 쏟아내는개구쟁이 하영이 자체가 예술이예요연우는 어른",
        "writer": "Ugwp7wWWJAQM8aaOGxV4AaABAg",
        "write_date": "2021-06-18",
        "url": "https://www.youtube.com/channel/UCK1sVuXaDvJeNwl9noN5nOA",
        "parent_url": "https://www.youtube.com/watch?v=ZnmqK4NPIro",
        "source_site": "https://www.youtube.com/"
      },
      {
        "content": "오(비속어) 아빠보다도 자상해요 , 나두 저런오빠 있음 말 잘들을 텐데,",
        "writer": "UgzVBApKkrqV4zxmtvJ4AaABAg",
        "write_date": "2021-06-18",
        "url": "https://www.youtube.com/channel/UCK1sVuXaDvJeNwl9noN5nOA",
        "parent_url": "https://www.youtube.com/watch?v=ZnmqK4NPIro",
        "source_site": "https://www.youtube.com/"
      },
      {
        "content": "하영이가집안에국민한태 행복을준다",
        "writer": "UgxZKSp_lryUkysQgMl4AaABAg",
        "write_date": "2021-06-18",
        "url": "https://www.youtube.com/channel/UCK1sVuXaDvJeNwl9noN5nOA",
        "parent_url": "https://www.youtube.com/watch?v=ZnmqK4NPIro",
        "source_site": "https://www.youtube.com/"
      },
      {
        "content": "하영아너무예쁘구나 그대로 잘크길.",
        "writer": "UgxwW2zR03h08hpM0iF4AaABAg",
        "write_date": "2021-06-18",
        "url": "https://www.youtube.com/channel/UCK1sVuXaDvJeNwl9noN5nOA",
        "parent_url": "https://www.youtube.com/watch?v=ZnmqK4NPIro",
        "source_site": "https://www.youtube.com/"
      },
      {
        "content": "이뻐 죽겠어.. 연우하영 건강해요",
        "writer": "Ugw8Z-YK8whGPniZohB4AaABAg",
        "write_date": "2021-05-18",
        "url": "https://www.youtube.com/channel/UCK1sVuXaDvJeNwl9noN5nOA",
        "parent_url": "https://www.youtube.com/watch?v=ZnmqK4NPIro",
        "source_site": "https://www.youtube.com/"
      },
      {
        "content": "연우는 어쩜 말도 저렇게 예쁘게 할까",
        "writer": "UgyOX4bV___IsGLRvT54AaABAg",
        "write_date": "2021-05-18",
        "url": "https://www.youtube.com/channel/UCK1sVuXaDvJeNwl9noN5nOA",
        "parent_url": "https://www.youtube.com/watch?v=ZnmqK4NPIro",
        "source_site": "https://www.youtube.com/"
      },
      {
        "content": "오빠 연우 너무착해요",
        "writer": "UgwRn0BJOG3vDyr6qKJ4AaABAg",
        "write_date": "2021-05-18",
        "url": "https://www.youtube.com/channel/UCK1sVuXaDvJeNwl9noN5nOA",
        "parent_url": "https://www.youtube.com/watch?v=ZnmqK4NPIro",
        "source_site": "https://www.youtube.com/"
      },
      {
        "content": "아넘넘귀요미 어캐요",
        "writer": "UgwWhuSuPPavx9FTfS14AaABAg",
        "write_date": "2021-05-18",
        "url": "https://www.youtube.com/channel/UCK1sVuXaDvJeNwl9noN5nOA",
        "parent_url": "https://www.youtube.com/watch?v=ZnmqK4NPIro",
        "source_site": "https://www.youtube.com/"
      },
      {
        "content": "장(이름) 하나 더 낳아 보세요 셋째는 또 어떤 영특하고 천재적인 아이가 낳으실지 능력도 되시고요. (이름)이 그렇게 원하시는되요",
        "writer": "UgyInwFOeM89n9w_ni14AaABAg",
        "write_date": "2021-05-18",
        "url": "https://www.youtube.com/channel/UCK1sVuXaDvJeNwl9noN5nOA",
        "parent_url": "https://www.youtube.com/watch?v=ZnmqK4NPIro",
        "source_site": "https://www.youtube.com/"
      },
      {
        "content": "장(이름) 부럽습니다 멋진 남편 똑똑하고 사랑이 가득한 두 아이 들 정말 성공하셨네요",
        "writer": "Ugz8IPBlxvF4xPAvWBF4AaABAg",
        "write_date": "2021-05-18",
        "url": "https://www.youtube.com/channel/UCK1sVuXaDvJeNwl9noN5nOA",
        "parent_url": "https://www.youtube.com/watch?v=ZnmqK4NPIro",
        "source_site": "https://www.youtube.com/"
      },
      {
        "content": "너무나 환상적인 조합",
        "writer": "UgygQzX0Wft1F9DyyVl4AaABAg",
        "write_date": "2021-05-18",
        "url": "https://www.youtube.com/channel/UCK1sVuXaDvJeNwl9noN5nOA",
        "parent_url": "https://www.youtube.com/watch?v=ZnmqK4NPIro",
        "source_site": "https://www.youtube.com/"
      },
      {
        "content": "하영이 넘 귀엽고 사랑스러워",
        "writer": "UgwyUvgxJAi5tVS-6Bd4AaABAg",
        "write_date": "2021-05-18",
        "url": "https://www.youtube.com/channel/UCK1sVuXaDvJeNwl9noN5nOA",
        "parent_url": "https://www.youtube.com/watch?v=ZnmqK4NPIro",
        "source_site": "https://www.youtube.com/"
      },
      {
        "content": "봐도 또봐도 재미있어요 이세상에 저런가족 또 있을까요 늘 감동입니다 현명하고 자상하고 인내심 강한 아빠 동생을 아끼고 사랑하는 오빠에 항상 감동과 재미가 넘칩니다",
        "writer": "UgxK-7FneLjui0D58e54AaABAg",
        "write_date": "2021-05-18",
        "url": "https://www.youtube.com/channel/UCK1sVuXaDvJeNwl9noN5nOA",
        "parent_url": "https://www.youtube.com/watch?v=ZnmqK4NPIro",
        "source_site": "https://www.youtube.com/"
      },
      {
        "content": "보고 싶어요",
        "writer": "Ugx7092D4XfRT6nU9Wd4AaABAg",
        "write_date": "2021-05-18",
        "url": "https://www.youtube.com/channel/UCK1sVuXaDvJeNwl9noN5nOA",
        "parent_url": "https://www.youtube.com/watch?v=ZnmqK4NPIro",
        "source_site": "https://www.youtube.com/"
      },
      {
        "content": "비록 애기들이지만 배울점이넘않아요 연우 너어 멋져.장(이름). 두분작품넘넘 멋져요 한나 더있음 어던작품일지 궁금",
        "writer": "UgwVL96EW8WnygJs9Ih4AaABAg",
        "write_date": "2021-05-18",
        "url": "https://www.youtube.com/channel/UCK1sVuXaDvJeNwl9noN5nOA",
        "parent_url": "https://www.youtube.com/watch?v=ZnmqK4NPIro",
        "source_site": "https://www.youtube.com/"
      },
      {
        "content": "도경완 (이름)부부 사랑스런연우 하영이와 행복 만땅 하세요",
        "writer": "UgybyrmICW(반사회적용어)kKJaOHJ4AaABAg",
        "write_date": "2021-05-18",
        "url": "https://www.youtube.com/channel/UCK1sVuXaDvJeNwl9noN5nOA",
        "parent_url": "https://www.youtube.com/watch?v=ZnmqK4NPIro",
        "source_site": "https://www.youtube.com/"
      },
      {
        "content": "하영이보는 재미로사는대 하영이가 (이름)다니 안돼요",
        "writer": "Ugx2OZyNl1Tm6VxezKF4AaABAg",
        "write_date": "2021-05-18",
        "url": "https://www.youtube.com/channel/UCK1sVuXaDvJeNwl9noN5nOA",
        "parent_url": "https://www.youtube.com/watch?v=ZnmqK4NPIro",
        "source_site": "https://www.youtube.com/"
      },
      {
        "content": "하영 연우 너무 이쁘다 (이름)니 세째는없나요 난 이런아가만낳을수만있다면 열명도좋아요",
        "writer": "UgyXVaA95CgHltE6jG54AaABAg",
        "write_date": "2021-05-18",
        "url": "https://www.youtube.com/channel/UCK1sVuXaDvJeNwl9noN5nOA",
        "parent_url": "https://www.youtube.com/watch?v=ZnmqK4NPIro",
        "source_site": "https://www.youtube.com/"
      },
      {
        "content": "와 연우 동생 생각 방석 갔다준다",
        "writer": "UgwxEQyPyj8Ew4-P3QR4AaABAg",
        "write_date": "2021-05-18",
        "url": "https://www.youtube.com/channel/UCK1sVuXaDvJeNwl9noN5nOA",
        "parent_url": "https://www.youtube.com/watch?v=ZnmqK4NPIro",
        "source_site": "https://www.youtube.com/"
      },
      {
        "content": "하영 (이름)",
        "writer": "UgyPixbg6PaYS2IG0td4AaABAg",
        "write_date": "2021-05-18",
        "url": "https://www.youtube.com/channel/UCK1sVuXaDvJeNwl9noN5nOA",
        "parent_url": "https://www.youtube.com/watch?v=ZnmqK4NPIro",
        "source_site": "https://www.youtube.com/"
      },
      {
        "content": "연우 어른스럽고 하영 귀엽",
        "writer": "UgxvI5twOO5AAgBMuCx4AaABAg",
        "write_date": "2021-05-18",
        "url": "https://www.youtube.com/channel/UCK1sVuXaDvJeNwl9noN5nOA",
        "parent_url": "https://www.youtube.com/watch?v=ZnmqK4NPIro",
        "source_site": "https://www.youtube.com/"
      },
      {
        "content": "하영인 재능있어 자연스런 탈랜트로, 정말 볼수록 사랑스럽다.",
        "writer": "UgwXapSleNFBcfbNw_94AaABAg",
        "write_date": "2021-05-18",
        "url": "https://www.youtube.com/channel/UCK1sVuXaDvJeNwl9noN5nOA",
        "parent_url": "https://www.youtube.com/watch?v=ZnmqK4NPIro",
        "source_site": "https://www.youtube.com/"
      },
      {
        "content": "우리 하영이 애교 민점 연기자 어쩜 말을저렇게 잘해 최 연소 엠씨 도경환 아빠의 피가 맞어요",
        "writer": "Ugw3hRCGM3z901BqCvh4AaABAg",
        "write_date": "2021-05-18",
        "url": "https://www.youtube.com/channel/UCK1sVuXaDvJeNwl9noN5nOA",
        "parent_url": "https://www.youtube.com/watch?v=ZnmqK4NPIro",
        "source_site": "https://www.youtube.com/"
      },
      {
        "content": "도(이름)두애들을 잘키우네요 최고의작품들이네요",
        "writer": "UgzY0kAR-V_NkHv3kXJ4AaABAg",
        "write_date": "2021-04-18",
        "url": "https://www.youtube.com/channel/UCK1sVuXaDvJeNwl9noN5nOA",
        "parent_url": "https://www.youtube.com/watch?v=ZnmqK4NPIro",
        "source_site": "https://www.youtube.com/"
      },
      {
        "content": "연우 공감능력. 배려심이 진짜 남다르네요. 연우가 장르입니다.",
        "writer": "UgzXlSpqSd_0kpiwQa94AaABAg",
        "write_date": "2021-04-18",
        "url": "https://www.youtube.com/channel/UCK1sVuXaDvJeNwl9noN5nOA",
        "parent_url": "https://www.youtube.com/watch?v=ZnmqK4NPIro",
        "source_site": "https://www.youtube.com/"
      },
      {
        "content": "연우 하영이는 너무 사랑스럽다",
        "writer": "UgzOUJmaVvav4uIbOSZ4AaABAg",
        "write_date": "2021-04-18",
        "url": "https://www.youtube.com/channel/UCK1sVuXaDvJeNwl9noN5nOA",
        "parent_url": "https://www.youtube.com/watch?v=ZnmqK4NPIro",
        "source_site": "https://www.youtube.com/"
      },
      {
        "content": "아빠귀에 속닥속닥, 아무말도 안했어, . 아빠 내가 도와줄거야",
        "writer": "Ugwi-OmKdLNNLgE9iFB4AaABAg",
        "write_date": "2021-04-18",
        "url": "https://www.youtube.com/channel/UCK1sVuXaDvJeNwl9noN5nOA",
        "parent_url": "https://www.youtube.com/watch?v=ZnmqK4NPIro",
        "source_site": "https://www.youtube.com/"
      },
      {
        "content": "아이뻐죽겟넹 근심이 싹 잊혀짐",
        "writer": "UgxVHiZRcPP5mcm2uEF4AaABAg",
        "write_date": "2021-04-18",
        "url": "https://www.youtube.com/channel/UCK1sVuXaDvJeNwl9noN5nOA",
        "parent_url": "https://www.youtube.com/watch?v=ZnmqK4NPIro",
        "source_site": "https://www.youtube.com/"
      },
      {
        "content": "세상에 저런 오빠 또 없습니다 어쩜 남매가 저리도 다정 하게 지낼 수 있는지 복 많은 남자 미모가 출중한 아내와 똑똑(반사회적용어)매까지",
        "writer": "Ugz6tSUqrRQcw4ZYPNd4AaABAg",
        "write_date": "2021-04-18",
        "url": "https://www.youtube.com/channel/UCK1sVuXaDvJeNwl9noN5nOA",
        "parent_url": "https://www.youtube.com/watch?v=ZnmqK4NPIro",
        "source_site": "https://www.youtube.com/"
      },
      {
        "content": "연우 같은 오빠 있으면 좋겠다",
        "writer": "Ugy-hg67xdXn04_SlDp4AaABAg",
        "write_date": "2021-04-18",
        "url": "https://www.youtube.com/channel/UCK1sVuXaDvJeNwl9noN5nOA",
        "parent_url": "https://www.youtube.com/watch?v=ZnmqK4NPIro",
        "source_site": "https://www.youtube.com/"
      },
      {
        "content": "도경완씨 외조덕분에 장(이름)가 나날이 번창하는것 같아요 도경완씨 정말 므찐 남자입니다 가르친다고 다 되는것도 아닌데 연우랑 하영이를 보면 부모성갹을 알수 있는법 정말정말 계속 도가족 지금처럼 행복햇으면 좋겠습니다",
        "writer": "UgxMuPGM071-4gGtLYp4AaABAg",
        "write_date": "2021-04-18",
        "url": "https://www.youtube.com/channel/UCK1sVuXaDvJeNwl9noN5nOA",
        "parent_url": "https://www.youtube.com/watch?v=ZnmqK4NPIro",
        "source_site": "https://www.youtube.com/"
      },
      {
        "content": "엄마 아빠 닮아서 다들 착하고 너무 이쁘네요",
        "writer": "Ugwp6yJ3xWdNvXiLqPF4AaABAg",
        "write_date": "2021-04-18",
        "url": "https://www.youtube.com/channel/UCK1sVuXaDvJeNwl9noN5nOA",
        "parent_url": "https://www.youtube.com/watch?v=ZnmqK4NPIro",
        "source_site": "https://www.youtube.com/"
      },
      {
        "content": "키가 잘 닿지 않을거라고 연우가 방석을 하영에게 가져 앉히다니 , 배려의 끝판왕이시다.",
        "writer": "UgzzxQOj7EaJ2_ohXlt4AaABAg",
        "write_date": "2021-04-18",
        "url": "https://www.youtube.com/channel/UCK1sVuXaDvJeNwl9noN5nOA",
        "parent_url": "https://www.youtube.com/watch?v=ZnmqK4NPIro",
        "source_site": "https://www.youtube.com/"
      },
      {
        "content": "어쩜 연우 하영 그렇게 예쁘게 잘키우신지 장(이름) 넘 행복해보여요 애들이 어쩜 그리착하고 하영이땜에 미치겠어요 귀여워",
        "writer": "UgzgF0nEsWmBZBNmsD94AaABAg",
        "write_date": "2021-04-18",
        "url": "https://www.youtube.com/channel/UCK1sVuXaDvJeNwl9noN5nOA",
        "parent_url": "https://www.youtube.com/watch?v=ZnmqK4NPIro",
        "source_site": "https://www.youtube.com/"
      },
      {
        "content": "속닥속닥 이렇게 기여운 애기가 또 있을까 넘 사랑스럽다 하영아",
        "writer": "Ugzga11KTvxTZewjqKt4AaABAg",
        "write_date": "2021-04-18",
        "url": "https://www.youtube.com/channel/UCK1sVuXaDvJeNwl9noN5nOA",
        "parent_url": "https://www.youtube.com/watch?v=ZnmqK4NPIro",
        "source_site": "https://www.youtube.com/"
      },
      {
        "content": "우리 이쁜 연우",
        "writer": "Ugw9u7D0cIrVxKTyReJ4AaABAg",
        "write_date": "2021-04-18",
        "url": "https://www.youtube.com/channel/UCK1sVuXaDvJeNwl9noN5nOA",
        "parent_url": "https://www.youtube.com/watch?v=ZnmqK4NPIro",
        "source_site": "https://www.youtube.com/"
      },
      {
        "content": "연우 하영이는 하차아되요",
        "writer": "UgyzNTx7loFgiCgPJxJ4AaABAg",
        "write_date": "2021-04-18",
        "url": "https://www.youtube.com/channel/UCK1sVuXaDvJeNwl9noN5nOA",
        "parent_url": "https://www.youtube.com/watch?v=ZnmqK4NPIro",
        "source_site": "https://www.youtube.com/"
      },
      {
        "content": "누구도 따를자없다 돼끼 하영이의 언변을,",
        "writer": "UgwcIr-pNNGTVCS6Fjt4AaABAg",
        "write_date": "2021-03-18",
        "url": "https://www.youtube.com/channel/UCK1sVuXaDvJeNwl9noN5nOA",
        "parent_url": "https://www.youtube.com/watch?v=ZnmqK4NPIro",
        "source_site": "https://www.youtube.com/"
      },
      {
        "content": "연유 연유 달콤 사랑스런 아이 달달하고 사려깊은 연우 감수성 풍부 EQ IQ. 다 높은 아이",
        "writer": "Ugyb74ApryVRRAOIYfF4AaABAg",
        "write_date": "2021-03-18",
        "url": "https://www.youtube.com/channel/UCK1sVuXaDvJeNwl9noN5nOA",
        "parent_url": "https://www.youtube.com/watch?v=ZnmqK4NPIro",
        "source_site": "https://www.youtube.com/"
      },
      {
        "content": "하영이똑똑하고예쁘고얘기도잘하구 모든걸가지고태어났나봐요 좋아요",
        "writer": "UgxgT30TR3SLDJ5XcDZ4AaABAg",
        "write_date": "2021-03-18",
        "url": "https://www.youtube.com/channel/UCK1sVuXaDvJeNwl9noN5nOA",
        "parent_url": "https://www.youtube.com/watch?v=ZnmqK4NPIro",
        "source_site": "https://www.youtube.com/"
      },
      {
        "content": "아이고 귀여워라",
        "writer": "Ugzc7wTtGPt3Zd80kTV4AaABAg",
        "write_date": "2021-03-18",
        "url": "https://www.youtube.com/channel/UCK1sVuXaDvJeNwl9noN5nOA",
        "parent_url": "https://www.youtube.com/watch?v=ZnmqK4NPIro",
        "source_site": "https://www.youtube.com/"
      },
      {
        "content": "하영이 귀여워",
        "writer": "Ugx8POfxqI70q0twD3x4AaABAg",
        "write_date": "2021-03-18",
        "url": "https://www.youtube.com/channel/UCK1sVuXaDvJeNwl9noN5nOA",
        "parent_url": "https://www.youtube.com/watch?v=ZnmqK4NPIro",
        "source_site": "https://www.youtube.com/"
      },
      {
        "content": "이 두 남매를 보고있으면 모든 시름이 사라지고 눈물 겹도록 아름답고 평화롭다. 어쩌면 이 부부에게 이런 복을 주셨을까 아마 그간 많은 고생 마음찟는 아픔을 잊고 행복하라는 (이름)이 주신 큰 복인가 생각된다. 많은 행사에 지친 몸도 두 아이를 보면 눈 녹듯 사라져 아마 계속 강행군을 해도 힘이 나나보다. 이 가족 축복하고 사랑한다.",
        "writer": "UgxI4pxBoiViWXgl0iF4AaABAg",
        "write_date": "2021-03-18",
        "url": "https://www.youtube.com/channel/UCK1sVuXaDvJeNwl9noN5nOA",
        "parent_url": "https://www.youtube.com/watch?v=ZnmqK4NPIro",
        "source_site": "https://www.youtube.com/"
      },
      {
        "content": "연우 참 착하고 다정다강하다 하영이 어째 저래 귀여운 행동만 하는지 저절로 웃음이 나게하는 이쁜 가족이네요",
        "writer": "UgyPJm9FdWgNJ1ATUPN4AaABAg",
        "write_date": "2021-03-18",
        "url": "https://www.youtube.com/channel/UCK1sVuXaDvJeNwl9noN5nOA",
        "parent_url": "https://www.youtube.com/watch?v=ZnmqK4NPIro",
        "source_site": "https://www.youtube.com/"
      },
      {
        "content": "연우는 그만좀 나와라 이제 넘 컸자나 슈돌에는 안맞아",
        "writer": "UgxDMwkOaO2AbIWM9PN4AaABAg",
        "write_date": "2021-03-18",
        "url": "https://www.youtube.com/channel/UCK1sVuXaDvJeNwl9noN5nOA",
        "parent_url": "https://www.youtube.com/watch?v=ZnmqK4NPIro",
        "source_site": "https://www.youtube.com/"
      },
      {
        "content": "연우는 절대 혼내지마세요 하영이를 혼내시드(반사회적용어) 넘 넘 사랑 스러워요",
        "writer": "UgwgCYq41zmxvm8qy8F4AaABAg",
        "write_date": "2021-03-18",
        "url": "https://www.youtube.com/channel/UCK1sVuXaDvJeNwl9noN5nOA",
        "parent_url": "https://www.youtube.com/watch?v=ZnmqK4NPIro",
        "source_site": "https://www.youtube.com/"
      },
      {
        "content": "연우 하영이 못보면 무순재미로 살까",
        "writer": "UgxRNLZsHMUapCsGB0x4AaABAg",
        "write_date": "2021-03-18",
        "url": "https://www.youtube.com/channel/UCK1sVuXaDvJeNwl9noN5nOA",
        "parent_url": "https://www.youtube.com/watch?v=ZnmqK4NPIro",
        "source_site": "https://www.youtube.com/"
      },
      {
        "content": "힐링되는 가족입니다",
        "writer": "UgyZKMDt-BAD6ets02l4AaABAg",
        "write_date": "2021-03-18",
        "url": "https://www.youtube.com/channel/UCK1sVuXaDvJeNwl9noN5nOA",
        "parent_url": "https://www.youtube.com/watch?v=ZnmqK4NPIro",
        "source_site": "https://www.youtube.com/"
      },
      {
        "content": "미치겠다 이 쪼꼬미들 때문에, 어우야",
        "writer": "UgwfysA0gCriVm0Wp9N4AaABAg",
        "write_date": "2021-02-18",
        "url": "https://www.youtube.com/channel/UCK1sVuXaDvJeNwl9noN5nOA",
        "parent_url": "https://www.youtube.com/watch?v=ZnmqK4NPIro",
        "source_site": "https://www.youtube.com/"
      },
      {
        "content": "진짜 얼굴 빻았다",
        "writer": "UgyLmmtEZeoii1tjQBZ4AaABAg",
        "write_date": "2021-02-18",
        "url": "https://www.youtube.com/channel/UCK1sVuXaDvJeNwl9noN5nOA",
        "parent_url": "https://www.youtube.com/watch?v=ZnmqK4NPIro",
        "source_site": "https://www.youtube.com/"
      },
      {
        "content": "연우 하영이 하차 하면 무슨 재미로 살죠 하차 하면 안되요",
        "writer": "UgxKbe_Hk1MmXkNchs14AaABAg",
        "write_date": "2021-02-18",
        "url": "https://www.youtube.com/channel/UCK1sVuXaDvJeNwl9noN5nOA",
        "parent_url": "https://www.youtube.com/watch?v=ZnmqK4NPIro",
        "source_site": "https://www.youtube.com/"
      },
      {
        "content": "세상에 만6살밖에 안된 애가 어떻게 저런 센스가 나오지 ... 집에서 아(비속어) 어떻게 하는지 딱 보인다",
        "writer": "UgxWrsf36tsKHZAzu6R4AaABAg",
        "write_date": "2021-02-18",
        "url": "https://www.youtube.com/channel/UCK1sVuXaDvJeNwl9noN5nOA",
        "parent_url": "https://www.youtube.com/watch?v=ZnmqK4NPIro",
        "source_site": "https://www.youtube.com/"
      },
      {
        "content": "하영공주 보고싶다 사랑스런 남매들 정말아름다운 모습니다",
        "writer": "Ugwe6O1CdKssnW_utu14AaABAg",
        "write_date": "2021-02-18",
        "url": "https://www.youtube.com/channel/UCK1sVuXaDvJeNwl9noN5nOA",
        "parent_url": "https://www.youtube.com/watch?v=ZnmqK4NPIro",
        "source_site": "https://www.youtube.com/"
      },
      {
        "content": "머든 이렇게 창의적으로",
        "writer": "Ugyw_LSWviMDRQG5AEh4AaABAg",
        "write_date": "2021-02-18",
        "url": "https://www.youtube.com/channel/UCK1sVuXaDvJeNwl9noN5nOA",
        "parent_url": "https://www.youtube.com/watch?v=ZnmqK4NPIro",
        "source_site": "https://www.youtube.com/"
      },
      {
        "content": "오누이의 본보기",
        "writer": "UgyANZ0VcxuKzDcVoYl4AaABAg",
        "write_date": "2021-02-18",
        "url": "https://www.youtube.com/channel/UCK1sVuXaDvJeNwl9noN5nOA",
        "parent_url": "https://www.youtube.com/watch?v=ZnmqK4NPIro",
        "source_site": "https://www.youtube.com/"
      },
      {
        "content": "연우가 정말 남다릅니다 정말 아이 훈육을 잘 하시는도경완씨네요",
        "writer": "UgxQKnTDUQOqyq2qgMR4AaABAg",
        "write_date": "2021-02-18",
        "url": "https://www.youtube.com/channel/UCK1sVuXaDvJeNwl9noN5nOA",
        "parent_url": "https://www.youtube.com/watch?v=ZnmqK4NPIro",
        "source_site": "https://www.youtube.com/"
      },
      {
        "content": "하영이가 몇개월 표현이 대단타 이삐이삐",
        "writer": "UgyokbIgmrFqh0XK7VN4AaABAg",
        "write_date": "2021-02-18",
        "url": "https://www.youtube.com/channel/UCK1sVuXaDvJeNwl9noN5nOA",
        "parent_url": "https://www.youtube.com/watch?v=ZnmqK4NPIro",
        "source_site": "https://www.youtube.com/"
      },
      {
        "content": "하영이 아빠 엄청 피곤해 보여요",
        "writer": "UgwdnZcFN1kBGTcl7Yl4AaABAg",
        "write_date": "2021-02-18",
        "url": "https://www.youtube.com/channel/UCK1sVuXaDvJeNwl9noN5nOA",
        "parent_url": "https://www.youtube.com/watch?v=ZnmqK4NPIro",
        "source_site": "https://www.youtube.com/"
      },
      {
        "content": "하영이 넘귀여워 미치겠다 정말 연우는넘 젠틀",
        "writer": "UgxkLAZwSctXPt8lkzh4AaABAg",
        "write_date": "2021-02-18",
        "url": "https://www.youtube.com/channel/UCK1sVuXaDvJeNwl9noN5nOA",
        "parent_url": "https://www.youtube.com/watch?v=ZnmqK4NPIro",
        "source_site": "https://www.youtube.com/"
      },
      {
        "content": "하영이 연우보는 재미로 살아요 귀엽고 사랑스러운 비타민",
        "writer": "UgwnXyt6PYdGQgj-cVR4AaABAg",
        "write_date": "2021-02-18",
        "url": "https://www.youtube.com/channel/UCK1sVuXaDvJeNwl9noN5nOA",
        "parent_url": "https://www.youtube.com/watch?v=ZnmqK4NPIro",
        "source_site": "https://www.youtube.com/"
      },
      {
        "content": "하영이땜에 참말로 미치것다",
        "writer": "Ugzvqe8xg2BtvX1Qmi14AaABAg",
        "write_date": "2021-02-18",
        "url": "https://www.youtube.com/channel/UCK1sVuXaDvJeNwl9noN5nOA",
        "parent_url": "https://www.youtube.com/watch?v=ZnmqK4NPIro",
        "source_site": "https://www.youtube.com/"
      },
      {
        "content": "하영이도 너무 귀엽지만 연우가 진짜 착하네, 동생한테 양보도 잘하고 둘다 귀여웡",
        "writer": "UgyOcSxr9B3ihGP27Qp4AaABAg",
        "write_date": "2021-02-18",
        "url": "https://www.youtube.com/channel/UCK1sVuXaDvJeNwl9noN5nOA",
        "parent_url": "https://www.youtube.com/watch?v=ZnmqK4NPIro",
        "source_site": "https://www.youtube.com/"
      },
      {
        "content": "하영이 혜(이름) 비교되네 하영이 똑똑하고 귀엽다",
        "writer": "UgxhUWKq_SUSPahmWFV4AaABAg",
        "write_date": "2021-02-18",
        "url": "https://www.youtube.com/channel/UCK1sVuXaDvJeNwl9noN5nOA",
        "parent_url": "https://www.youtube.com/watch?v=ZnmqK4NPIro",
        "source_site": "https://www.youtube.com/"
      },
      {
        "content": "연우랑 하영이 보고 싶어요",
        "writer": "UgzTTH1nDOQFnUackrd4AaABAg",
        "write_date": "2021-02-18",
        "url": "https://www.youtube.com/channel/UCK1sVuXaDvJeNwl9noN5nOA",
        "parent_url": "https://www.youtube.com/watch?v=ZnmqK4NPIro",
        "source_site": "https://www.youtube.com/"
      },
      {
        "content": "수시번을봐도 으음다코메 아이구여워",
        "writer": "Ugy6-OchNL5FDJ4O1-14AaABAg",
        "write_date": "2021-02-18",
        "url": "https://www.youtube.com/channel/UCK1sVuXaDvJeNwl9noN5nOA",
        "parent_url": "https://www.youtube.com/watch?v=ZnmqK4NPIro",
        "source_site": "https://www.youtube.com/"
      },
      {
        "content": "하영이 어휘량은 연우오빠와 풍부한 대화였음와연우 대견하다",
        "writer": "Ugz5PeGgIl8Xk0wVBXZ4AaABAg",
        "write_date": "2021-02-18",
        "url": "https://www.youtube.com/channel/UCK1sVuXaDvJeNwl9noN5nOA",
        "parent_url": "https://www.youtube.com/watch?v=ZnmqK4NPIro",
        "source_site": "https://www.youtube.com/"
      },
      {
        "content": "연우 하영 이뻐요.",
        "writer": "Ugz6CwitRDf5652Z8h94AaABAg",
        "write_date": "2021-02-18",
        "url": "https://www.youtube.com/channel/UCK1sVuXaDvJeNwl9noN5nOA",
        "parent_url": "https://www.youtube.com/watch?v=ZnmqK4NPIro",
        "source_site": "https://www.youtube.com/"
      },
      {
        "content": "하영이 너무나 귀엽다 연우도 너무너무 똑똑하다 둘다 너무 사랑스럽다 ...",
        "writer": "Ugwnh8cCO3PE8BOQHvJ4AaABAg",
        "write_date": "2021-02-18",
        "url": "https://www.youtube.com/channel/UCK1sVuXaDvJeNwl9noN5nOA",
        "parent_url": "https://www.youtube.com/watch?v=ZnmqK4NPIro",
        "source_site": "https://www.youtube.com/"
      },
      {
        "content": "도경완(이름) 교육부장관으로 임명합니다",
        "writer": "UgzZsKr3Sn-9N95TRtd4AaABAg",
        "write_date": "2021-02-18",
        "url": "https://www.youtube.com/channel/UCK1sVuXaDvJeNwl9noN5nOA",
        "parent_url": "https://www.youtube.com/watch?v=ZnmqK4NPIro",
        "source_site": "https://www.youtube.com/"
      },
      {
        "content": "연우야어쩌면동생을그렇게 끔직히생각하고사랑해 너무예쁘다",
        "writer": "UgzQb3p81V9hZrTR7Nl4AaABAg",
        "write_date": "2021-02-18",
        "url": "https://www.youtube.com/channel/UCK1sVuXaDvJeNwl9noN5nOA",
        "parent_url": "https://www.youtube.com/watch?v=ZnmqK4NPIro",
        "source_site": "https://www.youtube.com/"
      },
      {
        "content": "하영이 언어천재 같아용 넘 귀여워",
        "writer": "UgxHjoCJWBTEOJWLPJ54AaABAg",
        "write_date": "2021-02-18",
        "url": "https://www.youtube.com/channel/UCK1sVuXaDvJeNwl9noN5nOA",
        "parent_url": "https://www.youtube.com/watch?v=ZnmqK4NPIro",
        "source_site": "https://www.youtube.com/"
      },
      {
        "content": "효녀딸 하영 넘 귀여워 연우 하영 아빠도 아가들 참 교육 잘해요 우리 귀여운 하영 사랑해요",
        "writer": "UgxK7eUhbSg3NOYOtVp4AaABAg",
        "write_date": "2021-02-18",
        "url": "https://www.youtube.com/channel/UCK1sVuXaDvJeNwl9noN5nOA",
        "parent_url": "https://www.youtube.com/watch?v=ZnmqK4NPIro",
        "source_site": "https://www.youtube.com/"
      },
      {
        "content": "애들이 어찌 저리 착하고 이쁠까요 보는 내내 입꼬리가 올라가네요 (이름) 육아가 최고입니다 아나운서님도 대성하세요 응원합니다",
        "writer": "UgyeI_EFwXcDx_Ga5h54AaABAg",
        "write_date": "2021-02-18",
        "url": "https://www.youtube.com/channel/UCK1sVuXaDvJeNwl9noN5nOA",
        "parent_url": "https://www.youtube.com/watch?v=ZnmqK4NPIro",
        "source_site": "https://www.youtube.com/"
      },
      {
        "content": "어떻게 저렇게 귀엽지큐1일1연우하영 필수,",
        "writer": "UgyJsluuej3_bR38R0R4AaABAg",
        "write_date": "2021-02-18",
        "url": "https://www.youtube.com/channel/UCK1sVuXaDvJeNwl9noN5nOA",
        "parent_url": "https://www.youtube.com/watch?v=ZnmqK4NPIro",
        "source_site": "https://www.youtube.com/"
      },
      {
        "content": "하영이는 사랑받는 딸 여동생의",
        "writer": "UgxlDnS34mQ7EQyATMp4AaABAg",
        "write_date": "2021-02-18",
        "url": "https://www.youtube.com/channel/UCK1sVuXaDvJeNwl9noN5nOA",
        "parent_url": "https://www.youtube.com/watch?v=ZnmqK4NPIro",
        "source_site": "https://www.youtube.com/"
      },
      {
        "content": "배려의 진수를 울..",
        "writer": "UgwXcMO1At7EWWMARUx4AaABAg",
        "write_date": "2021-02-18",
        "url": "https://www.youtube.com/channel/UCK1sVuXaDvJeNwl9noN5nOA",
        "parent_url": "https://www.youtube.com/watch?v=ZnmqK4NPIro",
        "source_site": "https://www.youtube.com/"
      },
      {
        "content": "산교육의 진수",
        "writer": "Ugx4jSj-d56O_MrC5HN4AaABAg",
        "write_date": "2021-02-18",
        "url": "https://www.youtube.com/channel/UCK1sVuXaDvJeNwl9noN5nOA",
        "parent_url": "https://www.youtube.com/watch?v=ZnmqK4NPIro",
        "source_site": "https://www.youtube.com/"
      },
      {
        "content": "진짜 좋은아빠",
        "writer": "UgwSIT8mPjCLLuSjZhh4AaABAg",
        "write_date": "2021-02-18",
        "url": "https://www.youtube.com/channel/UCK1sVuXaDvJeNwl9noN5nOA",
        "parent_url": "https://www.youtube.com/watch?v=ZnmqK4NPIro",
        "source_site": "https://www.youtube.com/"
      },
      {
        "content": "하영이 넘 이뻐용 연우 참 듬직하네. 하영이도 잘 챙겨주고. 건강하고 행복하세요.",
        "writer": "Ugx6NAizkxsFGlHduFh4AaABAg",
        "write_date": "2021-02-18",
        "url": "https://www.youtube.com/channel/UCK1sVuXaDvJeNwl9noN5nOA",
        "parent_url": "https://www.youtube.com/watch?v=ZnmqK4NPIro",
        "source_site": "https://www.youtube.com/"
      },
      {
        "content": "역시 화목한가정입니다 우리자녀들도 본보기 화이팅",
        "writer": "UgyQt5se-TBNs2G7JSp4AaABAg",
        "write_date": "2021-02-18",
        "url": "https://www.youtube.com/channel/UCK1sVuXaDvJeNwl9noN5nOA",
        "parent_url": "https://www.youtube.com/watch?v=ZnmqK4NPIro",
        "source_site": "https://www.youtube.com/"
      },
      {
        "content": "똑똑한 연우 (반사회적용어)같은 하영이 넘 넘 넘 이쁘고 귀엽다. 매일 매일 찍어서 올려주세요. 다른 유투부는 볼것도 없어요",
        "writer": "UgyNTiSYvihfCaSt2il4AaABAg",
        "write_date": "2021-02-18",
        "url": "https://www.youtube.com/channel/UCK1sVuXaDvJeNwl9noN5nOA",
        "parent_url": "https://www.youtube.com/watch?v=ZnmqK4NPIro",
        "source_site": "https://www.youtube.com/"
      },
      {
        "content": "도경.윤정둘사이 어쩜요렇게예쁜요정이대어났나요.연우는.보면 찬원이어릴적커가든모습생각나게해요.착하고 똑똑하고예의바르고 하영인.어쩜.말도예쁘게 하지만.애교.아우깨물고싶네.도.윤.두남매잘키우세요.너무예쁜애기들 보면.넘행복하시겠어요 행복하세요",
        "writer": "UgxL6VaHYyNpmI3vNnB4AaABAg",
        "write_date": "2021-02-18",
        "url": "https://www.youtube.com/channel/UCK1sVuXaDvJeNwl9noN5nOA",
        "parent_url": "https://www.youtube.com/watch?v=ZnmqK4NPIro",
        "source_site": "https://www.youtube.com/"
      },
      {
        "content": "연우는 사랑 받은걸 그대로 동생에게 돌려줍니다 방석 가져다주고 본인은 방석귀퉁이에 않고 우리연우 너무예뻐 연(반사회적용어)번 꼭 보고싶어요 (이름) 사랑합니다",
        "writer": "UgzBDmOTBrh7Qu9_SAV4AaABAg",
        "write_date": "2021-02-18",
        "url": "https://www.youtube.com/channel/UCK1sVuXaDvJeNwl9noN5nOA",
        "parent_url": "https://www.youtube.com/watch?v=ZnmqK4NPIro",
        "source_site": "https://www.youtube.com/"
      },
      {
        "content": "어쩜저리 귀엽지 하는거마다 다 이쁜짖 하영아 사랑합니다",
        "writer": "Ugw5b-MLH_JOoPCQQ9N4AaABAg",
        "write_date": "2021-02-18",
        "url": "https://www.youtube.com/channel/UCK1sVuXaDvJeNwl9noN5nOA",
        "parent_url": "https://www.youtube.com/watch?v=ZnmqK4NPIro",
        "source_site": "https://www.youtube.com/"
      },
      {
        "content": "재미있어아무때나볼수있고 연우네가족코믹",
        "writer": "Ugzikpss1wEz8g2PDEx4AaABAg",
        "write_date": "2021-01-18",
        "url": "https://www.youtube.com/channel/UCK1sVuXaDvJeNwl9noN5nOA",
        "parent_url": "https://www.youtube.com/watch?v=ZnmqK4NPIro",
        "source_site": "https://www.youtube.com/"
      },
      {
        "content": "연우는 진짜 어린애가 넘 똘똘하고 생각이 깊어 저런아들이 어딨을까",
        "writer": "UgzKANnSMxfZlpomgo14AaABAg",
        "write_date": "2021-01-18",
        "url": "https://www.youtube.com/channel/UCK1sVuXaDvJeNwl9noN5nOA",
        "parent_url": "https://www.youtube.com/watch?v=ZnmqK4NPIro",
        "source_site": "https://www.youtube.com/"
      },
      {
        "content": "하영이 어쩜 말을 넘예쁘게하네요 밀가루 단어말할때 반해버렸어요 사랑스런 귀염둥이 하영이",
        "writer": "Ugwp3HKpwT8iYKdf0hV4AaABAg",
        "write_date": "2021-01-18",
        "url": "https://www.youtube.com/channel/UCK1sVuXaDvJeNwl9noN5nOA",
        "parent_url": "https://www.youtube.com/watch?v=ZnmqK4NPIro",
        "source_site": "https://www.youtube.com/"
      },
      {
        "content": "넘 예쁘다 연우랑하영이",
        "writer": "Ugz0jS4C72S3cbEZeid4AaABAg",
        "write_date": "2021-01-18",
        "url": "https://www.youtube.com/channel/UCK1sVuXaDvJeNwl9noN5nOA",
        "parent_url": "https://www.youtube.com/watch?v=ZnmqK4NPIro",
        "source_site": "https://www.youtube.com/"
      },
      {
        "content": "하영이 땜에 웃어요어쩜 저리 말도 잘하는지 넘 귀엽고 예뻐요연우도 너무 달콤하고 웃는 아빠도 보기좋고",
        "writer": "Ugyvxv5rpkxRiw1ZRrR4AaABAg",
        "write_date": "2021-01-18",
        "url": "https://www.youtube.com/channel/UCK1sVuXaDvJeNwl9noN5nOA",
        "parent_url": "https://www.youtube.com/watch?v=ZnmqK4NPIro",
        "source_site": "https://www.youtube.com/"
      },
      {
        "content": "정말 부러운 가정인넹요",
        "writer": "UgzBDmOTBrh7Qu9_SAV4AaABAg.9IdEkim6c_y9NsiPhWcHvB",
        "write_date": "2021-06-18",
        "url": "https://www.youtube.com/channel/UCK1sVuXaDvJeNwl9noN5nOA",
        "parent_url": "https://www.youtube.com/watch?v=ZnmqK4NPIro",
        "source_site": "https://www.youtube.com/"
      },
      {
        "content": "연우하영이넘이쁘고사랑스러워요 귀요미귀요미 늘(이름)응원합니다 (이름)남편분도대단하세요늘영원토록행복만땅하시고(이름)래건행하세요사랑합니다",
        "writer": "UgzBDmOTBrh7Qu9_SAV4AaABAg.9IdEkim6c_y9O2oMOurx8S",
        "write_date": "2021-06-18",
        "url": "https://www.youtube.com/channel/UCK1sVuXaDvJeNwl9noN5nOA",
        "parent_url": "https://www.youtube.com/watch?v=ZnmqK4NPIro",
        "source_site": "https://www.youtube.com/"
      },
      {
        "content": "연우 바르고 똑똑하고 하영이. 말잘하고 귀엽고. 두남매가 사랑스럽고. 웃음과.행복을 주네 넘.",
        "writer": "UgzqIJaVkWyr3sR6jHJ4AaABAg",
        "write_date": "2021-01-18",
        "url": "https://www.youtube.com/channel/UCK1sVuXaDvJeNwl9noN5nOA",
        "parent_url": "https://www.youtube.com/watch?v=ZnmqK4NPIro",
        "source_site": "https://www.youtube.com/"
      },
      {
        "content": "연우 어쩜 이렇게 사랑스러(비속어), 하영이 영원히 지켜주는 듬직한 오(비속어) 되어줘 연우야",
        "writer": "UgySOVACN7eMShy7dDp4AaABAg",
        "write_date": "2021-01-18",
        "url": "https://www.youtube.com/channel/UCK1sVuXaDvJeNwl9noN5nOA",
        "parent_url": "https://www.youtube.com/watch?v=ZnmqK4NPIro",
        "source_site": "https://www.youtube.com/"
      },
      {
        "content": "내가하영이때문(비속어)쵸 저렇게귀여울수도있나 아고 울하영이넘이뻐",
        "writer": "Ugxldr1BoeENhXYnBr94AaABAg",
        "write_date": "2021-01-18",
        "url": "https://www.youtube.com/channel/UCK1sVuXaDvJeNwl9noN5nOA",
        "parent_url": "https://www.youtube.com/watch?v=ZnmqK4NPIro",
        "source_site": "https://www.youtube.com/"
      },
      {
        "content": "내 삶에 하영이 같은 딸 없는게 두고두고 슬픔 입니다 두아들놈 귀여움 없어 졌는데 하영이 같은 딸 키우고파여",
        "writer": "Ugxilwp4aUMKwnBJ86t4AaABAg",
        "write_date": "2021-01-18",
        "url": "https://www.youtube.com/channel/UCK1sVuXaDvJeNwl9noN5nOA",
        "parent_url": "https://www.youtube.com/watch?v=ZnmqK4NPIro",
        "source_site": "https://www.youtube.com/"
      },
      {
        "content": "아유 하영이 어쩜 저래 이뿔까 남매가 아주 보물이다",
        "writer": "UgwboHlTmThJ22Rj3pR4AaABAg",
        "write_date": "2021-01-18",
        "url": "https://www.youtube.com/channel/UCK1sVuXaDvJeNwl9noN5nOA",
        "parent_url": "https://www.youtube.com/watch?v=ZnmqK4NPIro",
        "source_site": "https://www.youtube.com/"
      },
      {
        "content": "엔돌핀팍팍 울하영이 연우 이모가 진짜로 보고파용",
        "writer": "UgzNz17qNRTIwZUeoK94AaABAg",
        "write_date": "2021-01-18",
        "url": "https://www.youtube.com/channel/UCK1sVuXaDvJeNwl9noN5nOA",
        "parent_url": "https://www.youtube.com/watch?v=ZnmqK4NPIro",
        "source_site": "https://www.youtube.com/"
      },
      {
        "content": "대(이름) 아빠중에 도경완씨 최고로 아이 잘 키우는것 같아요 장(이름) 결혼 정말 잘했어요 프리선언 하고 아이만 잘 키워도 될듯, ..",
        "writer": "Ugx6CKJ7U04_NBsj1_J4AaABAg",
        "write_date": "2021-01-18",
        "url": "https://www.youtube.com/channel/UCK1sVuXaDvJeNwl9noN5nOA",
        "parent_url": "https://www.youtube.com/watch?v=ZnmqK4NPIro",
        "source_site": "https://www.youtube.com/"
      },
      {
        "content": "표현력이 끝내주는 하영이 귀여움폭팔 요즘 하영이 때문에 웃고삽니다 어찌 저렇게 말을 잘할까 어른인 나보다 표현력이 더 좋구나",
        "writer": "UgzF0hNGFe-6Flb1pCh4AaABAg",
        "write_date": "2021-01-18",
        "url": "https://www.youtube.com/channel/UCK1sVuXaDvJeNwl9noN5nOA",
        "parent_url": "https://www.youtube.com/watch?v=ZnmqK4NPIro",
        "source_site": "https://www.youtube.com/"
      },
      {
        "content": "어느 여자가 얼굴도 안나오며 소게하는 방송에서 도경환씨 직장 그만두고 이혼 했다해서 왜 하고 끝까지 봤는데 더이상 이혼말은 안해 거짓말해서 본인 방송 보라고 (반사회적용어) 참 한심하다 남에 가정을, 큰일나는거줘 본인 욕심을 채우기 위해 거짓말을 한번 들키면 다시는 안보줘 나쁜짓 하지마라",
        "writer": "Ugwxbmq8ouFkFEJURQ94AaABAg",
        "write_date": "2021-01-18",
        "url": "https://www.youtube.com/channel/UCK1sVuXaDvJeNwl9noN5nOA",
        "parent_url": "https://www.youtube.com/watch?v=ZnmqK4NPIro",
        "source_site": "https://www.youtube.com/"
      },
      {
        "content": "어쩜 아들 딸이 저렇게 예쁠까요 엄마 아(비속어) 잘 해서 그렇겎죠 가족모두 새해 복 많이 받으시고 건강하세요 즐거운 주셔서 감사합니다",
        "writer": "UgynVypSCt0gQOQj4El4AaABAg",
        "write_date": "2021-01-18",
        "url": "https://www.youtube.com/channel/UCK1sVuXaDvJeNwl9noN5nOA",
        "parent_url": "https://www.youtube.com/watch?v=ZnmqK4NPIro",
        "source_site": "https://www.youtube.com/"
      },
      {
        "content": "너무도 사랑스러운 가족 가슴이 따뜻해지는,",
        "writer": "UgxiFNlEKw1hsbTlU_Z4AaABAg",
        "write_date": "2021-01-18",
        "url": "https://www.youtube.com/channel/UCK1sVuXaDvJeNwl9noN5nOA",
        "parent_url": "https://www.youtube.com/watch?v=ZnmqK4NPIro",
        "source_site": "https://www.youtube.com/"
      },
      {
        "content": "하영이 언어천재",
        "writer": "UgyTnyDXXtNKTuquC7x4AaABAg",
        "write_date": "2021-01-18",
        "url": "https://www.youtube.com/channel/UCK1sVuXaDvJeNwl9noN5nOA",
        "parent_url": "https://www.youtube.com/watch?v=ZnmqK4NPIro",
        "source_site": "https://www.youtube.com/"
      },
      {
        "content": "하영이 잘 챙겨주고 아빠 엄마 할아버지 할머니 모두 건강하고 도씨 가족들 새해에는 복 많이 받으세요.",
        "writer": "Ugwo5g7kLGwfFb39xdd4AaABAg",
        "write_date": "2021-01-18",
        "url": "https://www.youtube.com/channel/UCK1sVuXaDvJeNwl9noN5nOA",
        "parent_url": "https://www.youtube.com/watch?v=ZnmqK4NPIro",
        "source_site": "https://www.youtube.com/"
      },
      {
        "content": "다음 생에는 하영이같은 딸이내품에서 태어 났으면",
        "writer": "UgxwkvlNArw4wVKoyAp4AaABAg",
        "write_date": "2021-01-18",
        "url": "https://www.youtube.com/channel/UCK1sVuXaDvJeNwl9noN5nOA",
        "parent_url": "https://www.youtube.com/watch?v=ZnmqK4NPIro",
        "source_site": "https://www.youtube.com/"
      },
      {
        "content": "하영 이세상에서 제일 귀여워용 이뻐 죽겠어 애기가 말도 잘하고",
        "writer": "UgwP_Kt1IQAvIzXq7wF4AaABAg",
        "write_date": "2021-01-18",
        "url": "https://www.youtube.com/channel/UCK1sVuXaDvJeNwl9noN5nOA",
        "parent_url": "https://www.youtube.com/watch?v=ZnmqK4NPIro",
        "source_site": "https://www.youtube.com/"
      },
      {
        "content": "도연우 세상최고 하영사랑 (이름) .복 받아 행복해 보느이도 행복 합니다",
        "writer": "Ugxv1oOS5wVIOBMPFu14AaABAg",
        "write_date": "2021-01-18",
        "url": "https://www.youtube.com/channel/UCK1sVuXaDvJeNwl9noN5nOA",
        "parent_url": "https://www.youtube.com/watch?v=ZnmqK4NPIro",
        "source_site": "https://www.youtube.com/"
      },
      {
        "content": "도하영 어쩜 그리도 귀여울까 도경환 아빠 꿀이 뚝뚝 떨어지고 얼굴에 행복이 뚝뚝 보기만도 행복 최고의 아빠 화이팅",
        "writer": "Ugy3cedfiJ6co8ZgKW94AaABAg",
        "write_date": "2021-01-18",
        "url": "https://www.youtube.com/channel/UCK1sVuXaDvJeNwl9noN5nOA",
        "parent_url": "https://www.youtube.com/watch?v=ZnmqK4NPIro",
        "source_site": "https://www.youtube.com/"
      },
      {
        "content": "이쁜 하영 연우 남매의 정석 귀엽고 배려하는 연우의 모습 너무 좋네요",
        "writer": "UgyU5gvpN7fIOtcGdfZ4AaABAg",
        "write_date": "2021-01-18",
        "url": "https://www.youtube.com/channel/UCK1sVuXaDvJeNwl9noN5nOA",
        "parent_url": "https://www.youtube.com/watch?v=ZnmqK4NPIro",
        "source_site": "https://www.youtube.com/"
      },
      {
        "content": "하차 하지 마요. 연우 하영이땜에 슈돌 보는데 하차는 아니 아니 아니되요",
        "writer": "UgxSOuBXxy_ZuYS2Yid4AaABAg",
        "write_date": "2021-01-18",
        "url": "https://www.youtube.com/channel/UCK1sVuXaDvJeNwl9noN5nOA",
        "parent_url": "https://www.youtube.com/watch?v=ZnmqK4NPIro",
        "source_site": "https://www.youtube.com/"
      },
      {
        "content": "무 귀여워 사랑스럽네",
        "writer": "Ugw5dBfOsOLU44fzCKp4AaABAg",
        "write_date": "2021-01-18",
        "url": "https://www.youtube.com/channel/UCK1sVuXaDvJeNwl9noN5nOA",
        "parent_url": "https://www.youtube.com/watch?v=ZnmqK4NPIro",
        "source_site": "https://www.youtube.com/"
      },
      {
        "content": "하영이의 음 달콤해 한마디에 쓰러집니다.",
        "writer": "Ugyy5-u-bT8SjFiOsk54AaABAg",
        "write_date": "2021-01-18",
        "url": "https://www.youtube.com/channel/UCK1sVuXaDvJeNwl9noN5nOA",
        "parent_url": "https://www.youtube.com/watch?v=ZnmqK4NPIro",
        "source_site": "https://www.youtube.com/"
      },
      {
        "content": "도연우 하영이 보느라 슈퍼맨이 돌아왔다 팬 됐어요",
        "writer": "UgyAnrwaPLFTTUhdHJ94AaABAg",
        "write_date": "2021-01-18",
        "url": "https://www.youtube.com/channel/UCK1sVuXaDvJeNwl9noN5nOA",
        "parent_url": "https://www.youtube.com/watch?v=ZnmqK4NPIro",
        "source_site": "https://www.youtube.com/"
      },
      {
        "content": "이렇게 귀여울수가 연우는 의젓하고 하영이는 귀엽고 장(이름)는 결혼하고 애기 낳고 더 잘되는거 같아요 남편 도경완씨가 맘껏 일할수 있게 외조를 해줘서 더욱 그런거 같아요 행복하세요",
        "writer": "UgwxcxA8HIJ1D_0vuCJ4AaABAg",
        "write_date": "2021-01-18",
        "url": "https://www.youtube.com/channel/UCK1sVuXaDvJeNwl9noN5nOA",
        "parent_url": "https://www.youtube.com/watch?v=ZnmqK4NPIro",
        "source_site": "https://www.youtube.com/"
      },
      {
        "content": "가빈예지현승병희길정 사랑해요 가빈예지현승병희길정 사랑해요 가빈예지현승병희길정 사랑해요 가빈예지현승병희길정 사랑해요 가빈예지현승병희길정 사랑해요 가빈예지현승병희길정 사랑해요 가빈예지현승병희길정 사랑해 사랑해 사랑해 사랑해 사랑한다 사랑해 사랑해 사랑한다 사랑해 사랑해 사랑한다 사랑한다 사랑해 사랑한다 사랑한다 사랑해 사랑한다 사랑한다 사랑해",
        "writer": "UgymH-uYRiAIE0nhH3h4AaABAg",
        "write_date": "2021-01-18",
        "url": "https://www.youtube.com/channel/UCK1sVuXaDvJeNwl9noN5nOA",
        "parent_url": "https://www.youtube.com/watch?v=ZnmqK4NPIro",
        "source_site": "https://www.youtube.com/"
      },
      {
        "content": "크브스 샹늠들아 하영이 출연시켜",
        "writer": "UgweVhKM-E-Bqd5d_HB4AaABAg",
        "write_date": "2021-01-18",
        "url": "https://www.youtube.com/channel/UCK1sVuXaDvJeNwl9noN5nOA",
        "parent_url": "https://www.youtube.com/watch?v=ZnmqK4NPIro",
        "source_site": "https://www.youtube.com/"
      },
      {
        "content": "하영이 음달코매",
        "writer": "UgxzIEqaxkSIhi86V4l4AaABAg",
        "write_date": "2021-01-18",
        "url": "https://www.youtube.com/channel/UCK1sVuXaDvJeNwl9noN5nOA",
        "parent_url": "https://www.youtube.com/watch?v=ZnmqK4NPIro",
        "source_site": "https://www.youtube.com/"
      },
      {
        "content": "좀 올리지 마라",
        "writer": "UgxYjnmGZksPkulH_PR4AaABAg",
        "write_date": "2021-01-18",
        "url": "https://www.youtube.com/channel/UCK1sVuXaDvJeNwl9noN5nOA",
        "parent_url": "https://www.youtube.com/watch?v=ZnmqK4NPIro",
        "source_site": "https://www.youtube.com/"
      },
      {
        "content": "하영이 서있어도 앉은 도라지보다 작은거 볼때마다 너무 귀여움",
        "writer": "UgyM6L6nLKpY4yQFbEF4AaABAg",
        "write_date": "2021-01-18",
        "url": "https://www.youtube.com/channel/UCK1sVuXaDvJeNwl9noN5nOA",
        "parent_url": "https://www.youtube.com/watch?v=ZnmqK4NPIro",
        "source_site": "https://www.youtube.com/"
      },
      {
        "content": "하영이는 볼매",
        "writer": "UgyJc9gXhkw1eOrXvdN4AaABAg",
        "write_date": "2021-01-18",
        "url": "https://www.youtube.com/channel/UCK1sVuXaDvJeNwl9noN5nOA",
        "parent_url": "https://www.youtube.com/watch?v=ZnmqK4NPIro",
        "source_site": "https://www.youtube.com/"
      },
      {
        "content": "이렇게 예쁜 울 연우. 하영이 못본다니 더 애착이 갑니다 다른 프로그램에서 꼭 볼수 있기를 기다릴게요 하영이 매력에 푸욱 빠진 이모예요",
        "writer": "UgzYtI_LeKcZOLEn7CR4AaABAg",
        "write_date": "2021-01-18",
        "url": "https://www.youtube.com/channel/UCK1sVuXaDvJeNwl9noN5nOA",
        "parent_url": "https://www.youtube.com/watch?v=ZnmqK4NPIro",
        "source_site": "https://www.youtube.com/"
      },
      {
        "content": "요즘 슈돌은 사랑스런 도화영 보는 맛에.",
        "writer": "Ugxk-iLiCmzOY5hC2Lp4AaABAg",
        "write_date": "2021-01-18",
        "url": "https://www.youtube.com/channel/UCK1sVuXaDvJeNwl9noN5nOA",
        "parent_url": "https://www.youtube.com/watch?v=ZnmqK4NPIro",
        "source_site": "https://www.youtube.com/"
      },
      {
        "content": "도하영 볼수록 귀엽고 사랑스러운 천사 입니다.",
        "writer": "Ugxi2W0p7TQk5XVvPNR4AaABAg",
        "write_date": "2021-01-18",
        "url": "https://www.youtube.com/channel/UCK1sVuXaDvJeNwl9noN5nOA",
        "parent_url": "https://www.youtube.com/watch?v=ZnmqK4NPIro",
        "source_site": "https://www.youtube.com/"
      },
      {
        "content": "하영이 훗날 커서 (이름)같은 가수가 될것 같아요",
        "writer": "Ugw-im_2Ts7U9BfPSWt4AaABAg",
        "write_date": "2021-01-18",
        "url": "https://www.youtube.com/channel/UCK1sVuXaDvJeNwl9noN5nOA",
        "parent_url": "https://www.youtube.com/watch?v=ZnmqK4NPIro",
        "source_site": "https://www.youtube.com/"
      },
      {
        "content": "도 장부부 넘 부럽네요 글구 연우 하영 넘나 바르게 키우셋네용",
        "writer": "Ugy6Nr6yV1Iio9CTzQJ4AaABAg",
        "write_date": "2021-01-18",
        "url": "https://www.youtube.com/channel/UCK1sVuXaDvJeNwl9noN5nOA",
        "parent_url": "https://www.youtube.com/watch?v=ZnmqK4NPIro",
        "source_site": "https://www.youtube.com/"
      },
      {
        "content": "연우는 진짜 배려돋는 오빠 사랑을 듬뿍받고 자라서 사랑을 나눠줄줄아는 아이 , 너무 이쁜 연우 하영이 올해도 건강하게 무럭무럭 자라자 ...",
        "writer": "Ugxdoq4BlL48XoL4r394AaABAg",
        "write_date": "2021-01-18",
        "url": "https://www.youtube.com/channel/UCK1sVuXaDvJeNwl9noN5nOA",
        "parent_url": "https://www.youtube.com/watch?v=ZnmqK4NPIro",
        "source_site": "https://www.youtube.com/"
      },
      {
        "content": "다정한 여누오빠 힝",
        "writer": "UgwF2yUq_3LzNOGMxKx4AaABAg",
        "write_date": "2021-01-18",
        "url": "https://www.youtube.com/channel/UCK1sVuXaDvJeNwl9noN5nOA",
        "parent_url": "https://www.youtube.com/watch?v=ZnmqK4NPIro",
        "source_site": "https://www.youtube.com/"
      },
      {
        "content": "보고있음 그냥 미소와 웃음이 절로 나와요, 넘 사랑스러운 아이들",
        "writer": "UgxYqQyXUBJTetege1t4AaABAg",
        "write_date": "2021-01-18",
        "url": "https://www.youtube.com/channel/UCK1sVuXaDvJeNwl9noN5nOA",
        "parent_url": "https://www.youtube.com/watch?v=ZnmqK4NPIro",
        "source_site": "https://www.youtube.com/"
      },
      {
        "content": "아무튼 하영이는 끼쟁이 너무 귀여워 깨물어 주고 싶어",
        "writer": "UgyAaVZ9AmOWqj993zp4AaABAg",
        "write_date": "2021-01-18",
        "url": "https://www.youtube.com/channel/UCK1sVuXaDvJeNwl9noN5nOA",
        "parent_url": "https://www.youtube.com/watch?v=ZnmqK4NPIro",
        "source_site": "https://www.youtube.com/"
      },
      {
        "content": "할머니가 몇일 옷봐서 보고싶어요. 말도 좀늘었겠지요.하영이는 말에 뜻을 다알고하는것같아서 더예뻐요. 짧은 단어지만 적절하게 표현을 내용에 맞게 잘하다라고요. 아빠의 재능을 닮아 아나우서 됐으면 좋겠다. 그리고 오(비속어) 마음이 여려서 하영이 한테는 모두 양보하는 오빠말 잘 듣는 하영이가 되자 아찌.",
        "writer": "UgzTkz14yy2wf3pRFkN4AaABAg",
        "write_date": "2021-01-18",
        "url": "https://www.youtube.com/channel/UCK1sVuXaDvJeNwl9noN5nOA",
        "parent_url": "https://www.youtube.com/watch?v=ZnmqK4NPIro",
        "source_site": "https://www.youtube.com/"
      },
      {
        "content": "애그귀염둥이 이쁘 죽겠어",
        "writer": "UgwGlUgccfjgKX0t5Ax4AaABAg",
        "write_date": "2021-01-18",
        "url": "https://www.youtube.com/channel/UCK1sVuXaDvJeNwl9noN5nOA",
        "parent_url": "https://www.youtube.com/watch?v=ZnmqK4NPIro",
        "source_site": "https://www.youtube.com/"
      },
      {
        "content": "귀에대고 무슨 이바구를 했나요. 아빠는 아무이야기도 안했다고 했는데. 아빠 도와준다고 어떻게 저렇게 말을 잘합니까.5살까지 귀여운 효도 다받으세요 국민여러분 하영이 저 이쁜짓 하는것보면.웃 음이 절로 나왔요 나영이 18번 왜.그래.왜.그래.",
        "writer": "UgwEMRIfwyku3mqnF-V4AaABAg",
        "write_date": "2021-01-18",
        "url": "https://www.youtube.com/channel/UCK1sVuXaDvJeNwl9noN5nOA",
        "parent_url": "https://www.youtube.com/watch?v=ZnmqK4NPIro",
        "source_site": "https://www.youtube.com/"
      },
      {
        "content": "도 화영 새배도 잘하는구만 엉등이도 같이",
        "writer": "Ugyprlaz5HqcvseBle94AaABAg",
        "write_date": "2021-01-18",
        "url": "https://www.youtube.com/channel/UCK1sVuXaDvJeNwl9noN5nOA",
        "parent_url": "https://www.youtube.com/watch?v=ZnmqK4NPIro",
        "source_site": "https://www.youtube.com/"
      },
      {
        "content": "남매가 저리 사이가 좋을 수 있다니 충격이다",
        "writer": "Ugxo8y9khzup5ecSRj14AaABAg",
        "write_date": "2021-01-18",
        "url": "https://www.youtube.com/channel/UCK1sVuXaDvJeNwl9noN5nOA",
        "parent_url": "https://www.youtube.com/watch?v=ZnmqK4NPIro",
        "source_site": "https://www.youtube.com/"
      },
      {
        "content": "매일매일 보고싶어지네요 행복(반사회적용어)",
        "writer": "UgzZVrOieG_iY-93ckl4AaABAg",
        "write_date": "2021-01-18",
        "url": "https://www.youtube.com/channel/UCK1sVuXaDvJeNwl9noN5nOA",
        "parent_url": "https://www.youtube.com/watch?v=ZnmqK4NPIro",
        "source_site": "https://www.youtube.com/"
      },
      {
        "content": "우리 연우는 정말 천사에요. 어쩜 저리도 동생에게 배려를 잘할까요",
        "writer": "UgzTImVHDlAgqmRZJ794AaABAg",
        "write_date": "2021-01-18",
        "url": "https://www.youtube.com/channel/UCK1sVuXaDvJeNwl9noN5nOA",
        "parent_url": "https://www.youtube.com/watch?v=ZnmqK4NPIro",
        "source_site": "https://www.youtube.com/"
      },
      {
        "content": "하영이 연우 모습오또케 넘잼나요",
        "writer": "Ugx7DSzWVNp5aiF9yER4AaABAg",
        "write_date": "2021-01-18",
        "url": "https://www.youtube.com/channel/UCK1sVuXaDvJeNwl9noN5nOA",
        "parent_url": "https://www.youtube.com/watch?v=ZnmqK4NPIro",
        "source_site": "https://www.youtube.com/"
      },
      {
        "content": "도 아나운서님도 아이들 잘키우시고 한가정에 남편으로써 연우하영이 아빠로써도, 건강하고 행복하세요",
        "writer": "UgzTkXn2oj2ytprxGER4AaABAg",
        "write_date": "2021-01-18",
        "url": "https://www.youtube.com/channel/UCK1sVuXaDvJeNwl9noN5nOA",
        "parent_url": "https://www.youtube.com/watch?v=ZnmqK4NPIro",
        "source_site": "https://www.youtube.com/"
      },
      {
        "content": "어휴 이뿌다 이뻐",
        "writer": "UgxamC8JZm1mtuHgPm14AaABAg",
        "write_date": "2021-01-18",
        "url": "https://www.youtube.com/channel/UCK1sVuXaDvJeNwl9noN5nOA",
        "parent_url": "https://www.youtube.com/watch?v=ZnmqK4NPIro",
        "source_site": "https://www.youtube.com/"
      },
      {
        "content": "가족은 행복합니다.",
        "writer": "UgytSXdoLAA7Iuw9yZN4AaABAg",
        "write_date": "2021-01-18",
        "url": "https://www.youtube.com/channel/UCK1sVuXaDvJeNwl9noN5nOA",
        "parent_url": "https://www.youtube.com/watch?v=ZnmqK4NPIro",
        "source_site": "https://www.youtube.com/"
      },
      {
        "content": "하영이 웃는거 넘 기여워요 완젼 입덕 포인트",
        "writer": "UgzY1AnNV8rO36-Dpbd4AaABAg",
        "write_date": "2021-01-18",
        "url": "https://www.youtube.com/channel/UCK1sVuXaDvJeNwl9noN5nOA",
        "parent_url": "https://www.youtube.com/watch?v=ZnmqK4NPIro",
        "source_site": "https://www.youtube.com/"
      },
      {
        "content": "진짜 너무 귀엽다 하영이 so sweet 연우 다정한 아빠 넘 행복해보여요",
        "writer": "UgwVwPX0SkrImjcpDel4AaABAg",
        "write_date": "2021-01-18",
        "url": "https://www.youtube.com/channel/UCK1sVuXaDvJeNwl9noN5nOA",
        "parent_url": "https://www.youtube.com/watch?v=ZnmqK4NPIro",
        "source_site": "https://www.youtube.com/"
      },
      {
        "content": "하영이네 진짜 하차하나요 사실이면 너무 슬퍼요 매주 연우 하영이보는 재미로사는데 잘생긴 우리연우 귀엽고 이쁘고 똑똑한 우리하영이 매주 얼마나 기대하는데이제 하영이보고싶으면 어떻게해요",
        "writer": "UgyDOJKQraxz_K5PId14AaABAg",
        "write_date": "2021-01-18",
        "url": "https://www.youtube.com/channel/UCK1sVuXaDvJeNwl9noN5nOA",
        "parent_url": "https://www.youtube.com/watch?v=ZnmqK4NPIro",
        "source_site": "https://www.youtube.com/"
      },
      {
        "content": "연우하차하면어떡해요.하영이보는재미로사는데.보고십으면어떡게하나요 가끔씩 이(반사회적용어)보여주세요.하영이너무너무좋와해요",
        "writer": "UgyGhgQyMnGg7VFXFzR4AaABAg",
        "write_date": "2021-01-18",
        "url": "https://www.youtube.com/channel/UCK1sVuXaDvJeNwl9noN5nOA",
        "parent_url": "https://www.youtube.com/watch?v=ZnmqK4NPIro",
        "source_site": "https://www.youtube.com/"
      },
      {
        "content": "하영이와 연우는 귀여움을 타고난 애기들이네요 남의 애들이(반사회적용어) 하는행동이 너무 이쁘네요 지금처럼만 예쁘게 자라기를 하영이가 어찌도 말을 이쁘게 귀엽게하는지 참으로 타고난 귀몀둥이네요",
        "writer": "UgwLD6YQDdWCMJLx2U94AaABAg",
        "write_date": "2021-01-18",
        "url": "https://www.youtube.com/channel/UCK1sVuXaDvJeNwl9noN5nOA",
        "parent_url": "https://www.youtube.com/watch?v=ZnmqK4NPIro",
        "source_site": "https://www.youtube.com/"
      },
      {
        "content": "아오 귀여운 하영이 사랑해 얘들아",
        "writer": "Ugzxde-cRjDLVHiln0l4AaABAg",
        "write_date": "2021-01-18",
        "url": "https://www.youtube.com/channel/UCK1sVuXaDvJeNwl9noN5nOA",
        "parent_url": "https://www.youtube.com/watch?v=ZnmqK4NPIro",
        "source_site": "https://www.youtube.com/"
      },
      {
        "content": "하영이 하루(반사회적용어) 안보면 보고 싶어요 . 도라지 가족 행복하게 사는 모습 참 좋아요 . 연우 하영 잘 길러 우리나라 중심 인물 되어 주세요 .",
        "writer": "UgwEMRIfwyku3mqnF-V4AaABAg.9IJ_abz6mTo9JFwpdwl4TW",
        "write_date": "2021-02-18",
        "url": "https://www.youtube.com/channel/UCK1sVuXaDvJeNwl9noN5nOA",
        "parent_url": "https://www.youtube.com/watch?v=ZnmqK4NPIro",
        "source_site": "https://www.youtube.com/"
      },
      {
        "content": "76세 할머니 하영이 한번 안아봤음 얼마나 좋을가요 속상할때도 하영 보면 기분",
        "writer": "UgwqhWL96Dhz27vu0l14AaABAg",
        "write_date": "2021-01-18",
        "url": "https://www.youtube.com/channel/UCK1sVuXaDvJeNwl9noN5nOA",
        "parent_url": "https://www.youtube.com/watch?v=ZnmqK4NPIro",
        "source_site": "https://www.youtube.com/"
      },
      {
        "content": "도하영 야시 우째저래 귀엽나요",
        "writer": "Ugwo8btbxStMWACk4MJ4AaABAg",
        "write_date": "2021-01-18",
        "url": "https://www.youtube.com/channel/UCK1sVuXaDvJeNwl9noN5nOA",
        "parent_url": "https://www.youtube.com/watch?v=ZnmqK4NPIro",
        "source_site": "https://www.youtube.com/"
      },
      {
        "content": "이시국에 연우. 하영이땜에 엔돌핀이 나와 우울함을 이기는데. 연우 하영이못보면 우린 어떻하라고. 하영이 계속 보게해쭈세요 제발용.",
        "writer": "Ugw1eWBC18cy6RpaJxB4AaABAg",
        "write_date": "2021-01-18",
        "url": "https://www.youtube.com/channel/UCK1sVuXaDvJeNwl9noN5nOA",
        "parent_url": "https://www.youtube.com/watch?v=ZnmqK4NPIro",
        "source_site": "https://www.youtube.com/"
      },
      {
        "content": "연우오빠 오늘도 (이름)인데 연우의 스윗함에 온세상이 따뜻해진단다",
        "writer": "UgxPvH_YrXZDOMdIMGt4AaABAg",
        "write_date": "2021-01-18",
        "url": "https://www.youtube.com/channel/UCK1sVuXaDvJeNwl9noN5nOA",
        "parent_url": "https://www.youtube.com/watch?v=ZnmqK4NPIro",
        "source_site": "https://www.youtube.com/"
      },
      {
        "content": "이런집에태어나면 이렇게 사랑받고 예쁘게살고, 부모도 이런애기들낳아서 복받고 애기들도 복받고 튼튼하게 건강하세요하영씨",
        "writer": "UgzgU9y1QBlchYl78lB4AaABAg",
        "write_date": "2021-01-18",
        "url": "https://www.youtube.com/channel/UCK1sVuXaDvJeNwl9noN5nOA",
        "parent_url": "https://www.youtube.com/watch?v=ZnmqK4NPIro",
        "source_site": "https://www.youtube.com/"
      },
      {
        "content": "귀여운 남매들 예뻐요",
        "writer": "UgwgqskjUgWS3fsEgi14AaABAg",
        "write_date": "2021-01-18",
        "url": "https://www.youtube.com/channel/UCK1sVuXaDvJeNwl9noN5nOA",
        "parent_url": "https://www.youtube.com/watch?v=ZnmqK4NPIro",
        "source_site": "https://www.youtube.com/"
      },
      {
        "content": "내 최애",
        "writer": "UgwuzaEWp1AdwDLSOsJ4AaABAg",
        "write_date": "2021-01-18",
        "url": "https://www.youtube.com/channel/UCK1sVuXaDvJeNwl9noN5nOA",
        "parent_url": "https://www.youtube.com/watch?v=ZnmqK4NPIro",
        "source_site": "https://www.youtube.com/"
      },
      {
        "content": "하영동생 사랑이 보기좋아요 철이 꽉 들었네요 하영 넘 귀여워.",
        "writer": "UgxHSC2x0rSyRLws2qx4AaABAg",
        "write_date": "2021-01-18",
        "url": "https://www.youtube.com/channel/UCK1sVuXaDvJeNwl9noN5nOA",
        "parent_url": "https://www.youtube.com/watch?v=ZnmqK4NPIro",
        "source_site": "https://www.youtube.com/"
      },
      {
        "content": "연우 하영이 말도 잘 하고 귀엽고 똑똑하고 예쁘네요",
        "writer": "UgwqMxy4AGxLLNYZVIV4AaABAg",
        "write_date": "2021-01-18",
        "url": "https://www.youtube.com/channel/UCK1sVuXaDvJeNwl9noN5nOA",
        "parent_url": "https://www.youtube.com/watch?v=ZnmqK4NPIro",
        "source_site": "https://www.youtube.com/"
      },
      {
        "content": "하늘이 주신 천사들 연우랑 하영이 건강하게 잘크렴",
        "writer": "Ugwp-nmFgXJ8WUG1cs54AaABAg",
        "write_date": "2021-01-18",
        "url": "https://www.youtube.com/channel/UCK1sVuXaDvJeNwl9noN5nOA",
        "parent_url": "https://www.youtube.com/watch?v=ZnmqK4NPIro",
        "source_site": "https://www.youtube.com/"
      },
      {
        "content": "보고있으면 웃음이 나와요 행복(반사회적용어)",
        "writer": "UgxN1Y5gClLcCGFJMSB4AaABAg",
        "write_date": "2021-01-18",
        "url": "https://www.youtube.com/channel/UCK1sVuXaDvJeNwl9noN5nOA",
        "parent_url": "https://www.youtube.com/watch?v=ZnmqK4NPIro",
        "source_site": "https://www.youtube.com/"
      },
      {
        "content": "저도 이 가족 왕팬인데요. 죄송하지만 도경환이 아니라 도경완 님입니다. 많은 분들이 잘못 알고 계셔서 알려드려요.",
        "writer": "Ugwpufmsr3C686Jb9QV4AaABAg",
        "write_date": "2021-01-18",
        "url": "https://www.youtube.com/channel/UCK1sVuXaDvJeNwl9noN5nOA",
        "parent_url": "https://www.youtube.com/watch?v=ZnmqK4NPIro",
        "source_site": "https://www.youtube.com/"
      },
      {
        "content": "(이름)가족 이젠 슈돌에서 못보겠네 아숩다 도경완 프리선언은 잘한거같은데. KBS는 3년간 출현못하잖아 근데 이거 너무한거아닌가 아님 법이 그런가 방송국들은 프리선언 하면 왜 출현 안되지 궁금하네",
        "writer": "Ugz8H3mxSaFt3QpK9Bl4AaABAg",
        "write_date": "2021-01-18",
        "url": "https://www.youtube.com/channel/UCK1sVuXaDvJeNwl9noN5nOA",
        "parent_url": "https://www.youtube.com/watch?v=ZnmqK4NPIro",
        "source_site": "https://www.youtube.com/"
      },
      {
        "content": "하영아 그고사리 손으로 만들겠다고 하영이가 만든 만두 먹고 싶어요 화이팅",
        "writer": "UgxCRz5fx8Mvrta2GuF4AaABAg",
        "write_date": "2021-01-18",
        "url": "https://www.youtube.com/channel/UCK1sVuXaDvJeNwl9noN5nOA",
        "parent_url": "https://www.youtube.com/watch?v=ZnmqK4NPIro",
        "source_site": "https://www.youtube.com/"
      },
      {
        "content": "애기들 정말 잘키우시네요 어릴적 환경이 아이인생을 좌우합니다 도 장부부 아이들 가정교육 정말 잘하고있어 아이들의 미래가 기대됩니다",
        "writer": "UgxVdArAHCLbNh_DHEh4AaABAg",
        "write_date": "2021-01-18",
        "url": "https://www.youtube.com/channel/UCK1sVuXaDvJeNwl9noN5nOA",
        "parent_url": "https://www.youtube.com/watch?v=ZnmqK4NPIro",
        "source_site": "https://www.youtube.com/"
      },
      {
        "content": "하영이때문에살아가는사람입니다 아침에눈뜨면유튜브보면서시작하네요 슈퍼멘하영이때문에보네요 항상그만큼만옆에있어줬으면좋겠어요 우리하영이내딸삼아서아침에눈뜨면유튜브에서빠져나오질못하고살고있어요 사랑해요 하영",
        "writer": "UgyTrn8MAKfx_jfoTHR4AaABAg",
        "write_date": "2021-01-18",
        "url": "https://www.youtube.com/channel/UCK1sVuXaDvJeNwl9noN5nOA",
        "parent_url": "https://www.youtube.com/watch?v=ZnmqK4NPIro",
        "source_site": "https://www.youtube.com/"
      },
      {
        "content": "연우는 미남자 하영이는 모냄이",
        "writer": "UgxWpRi9_NmKv2vc0mV4AaABAg",
        "write_date": "2021-01-18",
        "url": "https://www.youtube.com/channel/UCK1sVuXaDvJeNwl9noN5nOA",
        "parent_url": "https://www.youtube.com/watch?v=ZnmqK4NPIro",
        "source_site": "https://www.youtube.com/"
      },
      {
        "content": "귀에다 대고 아무 얘기도안했엌",
        "writer": "UgzFo7Cn3cnPvjloMZF4AaABAg",
        "write_date": "2021-01-18",
        "url": "https://www.youtube.com/channel/UCK1sVuXaDvJeNwl9noN5nOA",
        "parent_url": "https://www.youtube.com/watch?v=ZnmqK4NPIro",
        "source_site": "https://www.youtube.com/"
      },
      {
        "content": "하영이 계속 보고싶어요",
        "writer": "Ugz8H3mxSaFt3QpK9Bl4AaABAg.9IGvRzuSCJy9IP-6JgLJGx",
        "write_date": "2021-01-18",
        "url": "https://www.youtube.com/channel/UCK1sVuXaDvJeNwl9noN5nOA",
        "parent_url": "https://www.youtube.com/watch?v=ZnmqK4NPIro",
        "source_site": "https://www.youtube.com/"
      },
      {
        "content": "연우하영 새해도 건강하고사랑해용",
        "writer": "UgxXbVafXRvYPKv1Zi94AaABAg",
        "write_date": "2021-01-18",
        "url": "https://www.youtube.com/channel/UCK1sVuXaDvJeNwl9noN5nOA",
        "parent_url": "https://www.youtube.com/watch?v=ZnmqK4NPIro",
        "source_site": "https://www.youtube.com/"
      },
      {
        "content": "이렇(비속어)쁜 하영 연우를 이젠슈돌에서 보지못(이름) 넘넘서운하네요 연우 하영 이제몇편이나 볼래나 착(이름) 똑쨍(이름) 크가는모습 자주좀보여주세요 아빠도아나운서님",
        "writer": "UgybpXF11EaXbCQouUR4AaABAg",
        "write_date": "2021-01-18",
        "url": "https://www.youtube.com/channel/UCK1sVuXaDvJeNwl9noN5nOA",
        "parent_url": "https://www.youtube.com/watch?v=ZnmqK4NPIro",
        "source_site": "https://www.youtube.com/"
      },
      {
        "content": "하영이는 어쩜 저리도 말을 똘똘하게 잘하는지 하영이는 봐도봐도 보고싶은 사랑스런 애기예요",
        "writer": "UgxGaNovIIvy20A6-Ax4AaABAg",
        "write_date": "2021-01-18",
        "url": "https://www.youtube.com/channel/UCK1sVuXaDvJeNwl9noN5nOA",
        "parent_url": "https://www.youtube.com/watch?v=ZnmqK4NPIro",
        "source_site": "https://www.youtube.com/"
      },
      {
        "content": "연우아빠 하영이아빠 도경환아나운서님 최고의 아빠입니다 아니 대(이름)아빠 최고입니다 화이팅하세요",
        "writer": "UgxdofJjxgEicanU5v94AaABAg",
        "write_date": "2021-01-18",
        "url": "https://www.youtube.com/channel/UCK1sVuXaDvJeNwl9noN5nOA",
        "parent_url": "https://www.youtube.com/watch?v=ZnmqK4NPIro",
        "source_site": "https://www.youtube.com/"
      },
      {
        "content": "동생이 잘 (이름)다고 방석까지 같다주는 친절 연우씨 인성최고",
        "writer": "UgzbW-zLKq1qH04P4wB4AaABAg",
        "write_date": "2021-01-18",
        "url": "https://www.youtube.com/channel/UCK1sVuXaDvJeNwl9noN5nOA",
        "parent_url": "https://www.youtube.com/watch?v=ZnmqK4NPIro",
        "source_site": "https://www.youtube.com/"
      },
      {
        "content": "하영이네 계속계속 보고싶은 1인입니다",
        "writer": "Ugx9AruIsEp9KCcvvm94AaABAg",
        "write_date": "2021-01-18",
        "url": "https://www.youtube.com/channel/UCK1sVuXaDvJeNwl9noN5nOA",
        "parent_url": "https://www.youtube.com/watch?v=ZnmqK4NPIro",
        "source_site": "https://www.youtube.com/"
      },
      {
        "content": "우리 하영이 너무이뻐요",
        "writer": "UgxUhhJBu9tFQKsG4Q14AaABAg",
        "write_date": "2021-01-18",
        "url": "https://www.youtube.com/channel/UCK1sVuXaDvJeNwl9noN5nOA",
        "parent_url": "https://www.youtube.com/watch?v=ZnmqK4NPIro",
        "source_site": "https://www.youtube.com/"
      },
      {
        "content": "왜케 이쁘니하영아",
        "writer": "UgyFHpE1DMoyTMawM7t4AaABAg",
        "write_date": "2021-01-18",
        "url": "https://www.youtube.com/channel/UCK1sVuXaDvJeNwl9noN5nOA",
        "parent_url": "https://www.youtube.com/watch?v=ZnmqK4NPIro",
        "source_site": "https://www.youtube.com/"
      },
      {
        "content": "연우 하영이 보면 행동하나 하나 넘 귀엽고 둘다 의좋은 형제 자매 연우가 넘 철이 빨리들은 것같아요 어른스럽고 엄마 아빠 참 좋겠어요 아들 딸 보면 행복",
        "writer": "UgyjWIThbfTU88mkdFB4AaABAg",
        "write_date": "2021-01-18",
        "url": "https://www.youtube.com/channel/UCK1sVuXaDvJeNwl9noN5nOA",
        "parent_url": "https://www.youtube.com/watch?v=ZnmqK4NPIro",
        "source_site": "https://www.youtube.com/"
      },
      {
        "content": "요즘 코로나 때문에 사람들 마음이 어렵고 나(반사회적용어) 혼란스러운데 하영이를 보면서 웃고 위로가 됩니다 하영이 넘 귀엽고 꼭 (이름)고 싶어요 연우 하영이 넘 똑똑해요",
        "writer": "Ugx8YEXPwbLwsCxhfgt4AaABAg",
        "write_date": "2021-01-18",
        "url": "https://www.youtube.com/channel/UCK1sVuXaDvJeNwl9noN5nOA",
        "parent_url": "https://www.youtube.com/watch?v=ZnmqK4NPIro",
        "source_site": "https://www.youtube.com/"
      },
      {
        "content": "왜이러케 이뻐 그럼말을",
        "writer": "Ugzd7QRHamuYasv8JM94AaABAg",
        "write_date": "2021-01-18",
        "url": "https://www.youtube.com/channel/UCK1sVuXaDvJeNwl9noN5nOA",
        "parent_url": "https://www.youtube.com/watch?v=ZnmqK4NPIro",
        "source_site": "https://www.youtube.com/"
      },
      {
        "content": "지금부터 먹어볼까요 우찌요런말을",
        "writer": "Ugx3gx2pLkFu33E_ogl4AaABAg",
        "write_date": "2021-01-18",
        "url": "https://www.youtube.com/channel/UCK1sVuXaDvJeNwl9noN5nOA",
        "parent_url": "https://www.youtube.com/watch?v=ZnmqK4NPIro",
        "source_site": "https://www.youtube.com/"
      },
      {
        "content": "저런 귓속말도 안하면서 재치덩어리",
        "writer": "UgwFHxaejZFXFOwXV8J4AaABAg",
        "write_date": "2021-01-18",
        "url": "https://www.youtube.com/channel/UCK1sVuXaDvJeNwl9noN5nOA",
        "parent_url": "https://www.youtube.com/watch?v=ZnmqK4NPIro",
        "source_site": "https://www.youtube.com/"
      },
      {
        "content": "한쪽얼굴살짝 찌푸린듯 코실룩 표젱 넘이뻐으음 다코메",
        "writer": "UgxeDq0i2GpcvNihnup4AaABAg",
        "write_date": "2021-01-18",
        "url": "https://www.youtube.com/channel/UCK1sVuXaDvJeNwl9noN5nOA",
        "parent_url": "https://www.youtube.com/watch?v=ZnmqK4NPIro",
        "source_site": "https://www.youtube.com/"
      },
      {
        "content": "으응다코 메 꿀목소리",
        "writer": "Ugwb1bpr5ohFulWsIZF4AaABAg",
        "write_date": "2021-01-18",
        "url": "https://www.youtube.com/channel/UCK1sVuXaDvJeNwl9noN5nOA",
        "parent_url": "https://www.youtube.com/watch?v=ZnmqK4NPIro",
        "source_site": "https://www.youtube.com/"
      },
      {
        "content": "하영이 너무 귀여워요 하영아. 안 녕",
        "writer": "Ugy-1BAOQ80Cfrn0m2d4AaABAg",
        "write_date": "2021-01-18",
        "url": "https://www.youtube.com/channel/UCK1sVuXaDvJeNwl9noN5nOA",
        "parent_url": "https://www.youtube.com/watch?v=ZnmqK4NPIro",
        "source_site": "https://www.youtube.com/"
      },
      {
        "content": "너무 예쁘게 잘 키우시네요 너무 귀여워요",
        "writer": "Ugxy0susqOlwtg8mJbJ4AaABAg",
        "write_date": "2021-01-18",
        "url": "https://www.youtube.com/channel/UCK1sVuXaDvJeNwl9noN5nOA",
        "parent_url": "https://www.youtube.com/watch?v=ZnmqK4NPIro",
        "source_site": "https://www.youtube.com/"
      },
      {
        "content": "하영이 말하는거 보면 웃음이 절로나온다 너무 귀여워서 깨물고싶다",
        "writer": "UgyCHPh0ahmqM5aVSXh4AaABAg",
        "write_date": "2021-01-18",
        "url": "https://www.youtube.com/channel/UCK1sVuXaDvJeNwl9noN5nOA",
        "parent_url": "https://www.youtube.com/watch?v=ZnmqK4NPIro",
        "source_site": "https://www.youtube.com/"
      },
      {
        "content": "(이름)가 아주 우렁차요 밀가루 밀가루 아오 뽀뽀하고파라 쪽",
        "writer": "UgwQE1mQYpvktxxLFWl4AaABAg",
        "write_date": "2021-01-18",
        "url": "https://www.youtube.com/channel/UCK1sVuXaDvJeNwl9noN5nOA",
        "parent_url": "https://www.youtube.com/watch?v=ZnmqK4NPIro",
        "source_site": "https://www.youtube.com/"
      },
      {
        "content": "경환씨 가족보는재미로 이프로 봅니다 절대 하영이를 계속보게 하차하면 안됩니다",
        "writer": "UgweWtaEGd5G4ghkekl4AaABAg",
        "write_date": "2021-01-18",
        "url": "https://www.youtube.com/channel/UCK1sVuXaDvJeNwl9noN5nOA",
        "parent_url": "https://www.youtube.com/watch?v=ZnmqK4NPIro",
        "source_site": "https://www.youtube.com/"
      },
      {
        "content": "세상 저런오(비속어)있을까 나도 남매를 키웠지만 울아들은 저만알던데 진짜 이쁜아들 오빠",
        "writer": "UgxQrG6ds_LJ4rEa5rZ4AaABAg",
        "write_date": "2021-01-18",
        "url": "https://www.youtube.com/channel/UCK1sVuXaDvJeNwl9noN5nOA",
        "parent_url": "https://www.youtube.com/watch?v=ZnmqK4NPIro",
        "source_site": "https://www.youtube.com/"
      },
      {
        "content": "하영이 말하는것좀봐. 요거 물건일세",
        "writer": "Ugz8Kp_01bgjgKo0N4B4AaABAg",
        "write_date": "2021-01-18",
        "url": "https://www.youtube.com/channel/UCK1sVuXaDvJeNwl9noN5nOA",
        "parent_url": "https://www.youtube.com/watch?v=ZnmqK4NPIro",
        "source_site": "https://www.youtube.com/"
      },
      {
        "content": "연우 하영 절대로하차하면안되요",
        "writer": "UgyskPqXeaoN1EsbSAR4AaABAg",
        "write_date": "2021-01-18",
        "url": "https://www.youtube.com/channel/UCK1sVuXaDvJeNwl9noN5nOA",
        "parent_url": "https://www.youtube.com/watch?v=ZnmqK4NPIro",
        "source_site": "https://www.youtube.com/"
      },
      {
        "content": "연우 하영 참 이쁘네요 .",
        "writer": "Ugwn1CJKM_N71kBb6eJ4AaABAg",
        "write_date": "2021-01-18",
        "url": "https://www.youtube.com/channel/UCK1sVuXaDvJeNwl9noN5nOA",
        "parent_url": "https://www.youtube.com/watch?v=ZnmqK4NPIro",
        "source_site": "https://www.youtube.com/"
      },
      {
        "content": "하영 하영 하영 저 엉말 사랑스러움 그 자체예요 금년에 도 행복하고 건강한가족 응원합니다 화이팅",
        "writer": "UgxMwjUGNsG7iyF_8fN4AaABAg",
        "write_date": "2021-01-18",
        "url": "https://www.youtube.com/channel/UCK1sVuXaDvJeNwl9noN5nOA",
        "parent_url": "https://www.youtube.com/watch?v=ZnmqK4NPIro",
        "source_site": "https://www.youtube.com/"
      },
      {
        "content": "내가 종일 그렇구나. 하며 일 할 것 같아.",
        "writer": "UgwqK-oP8Pfn9L-Hqgd4AaABAg",
        "write_date": "2021-01-18",
        "url": "https://www.youtube.com/channel/UCK1sVuXaDvJeNwl9noN5nOA",
        "parent_url": "https://www.youtube.com/watch?v=ZnmqK4NPIro",
        "source_site": "https://www.youtube.com/"
      },
      {
        "content": "연우 하영이 계속 나오세요.",
        "writer": "UgwFfO05Q7B1S_g0moF4AaABAg",
        "write_date": "2021-01-18",
        "url": "https://www.youtube.com/channel/UCK1sVuXaDvJeNwl9noN5nOA",
        "parent_url": "https://www.youtube.com/watch?v=ZnmqK4NPIro",
        "source_site": "https://www.youtube.com/"
      },
      {
        "content": "세상에서 젤 부러운 (이름)",
        "writer": "Ugx_tvXojwFZfH0ghkB4AaABAg",
        "write_date": "2021-01-18",
        "url": "https://www.youtube.com/channel/UCK1sVuXaDvJeNwl9noN5nOA",
        "parent_url": "https://www.youtube.com/watch?v=ZnmqK4NPIro",
        "source_site": "https://www.youtube.com/"
      },
      {
        "content": "경완씨 연우 하영 안나옴 사는 낙이 없어요",
        "writer": "UgyZsM3IlYB66FcRTcB4AaABAg",
        "write_date": "2021-01-18",
        "url": "https://www.youtube.com/channel/UCK1sVuXaDvJeNwl9noN5nOA",
        "parent_url": "https://www.youtube.com/watch?v=ZnmqK4NPIro",
        "source_site": "https://www.youtube.com/"
      },
      {
        "content": "하영이땜에 더웃는다 .정말못하는 말이없네 . 정말 천재야 두아이가 인(비속어)육이 참되어있다.",
        "writer": "UgyLBpn6MtkXDx0FXdd4AaABAg",
        "write_date": "2021-01-18",
        "url": "https://www.youtube.com/channel/UCK1sVuXaDvJeNwl9noN5nOA",
        "parent_url": "https://www.youtube.com/watch?v=ZnmqK4NPIro",
        "source_site": "https://www.youtube.com/"
      },
      {
        "content": "귀에 서로속삭이는 모습사랑스러워요",
        "writer": "UgzVIN-w8Zoqmwt9Wmd4AaABAg",
        "write_date": "2021-01-18",
        "url": "https://www.youtube.com/channel/UCK1sVuXaDvJeNwl9noN5nOA",
        "parent_url": "https://www.youtube.com/watch?v=ZnmqK4NPIro",
        "source_site": "https://www.youtube.com/"
      },
      {
        "content": "귀에 속삭이는모습 너 고여워",
        "writer": "Ugw4DX7f3oVRGcAo41R4AaABAg",
        "write_date": "2021-01-18",
        "url": "https://www.youtube.com/channel/UCK1sVuXaDvJeNwl9noN5nOA",
        "parent_url": "https://www.youtube.com/watch?v=ZnmqK4NPIro",
        "source_site": "https://www.youtube.com/"
      },
      {
        "content": "도연우 도하영 에구 예쁜아가들 보고있으면입가에웃습이절 로나내요 연우아버님 존경합니다",
        "writer": "Ugz1if9ngLXk6m6wRYx4AaABAg",
        "write_date": "2021-01-18",
        "url": "https://www.youtube.com/channel/UCK1sVuXaDvJeNwl9noN5nOA",
        "parent_url": "https://www.youtube.com/watch?v=ZnmqK4NPIro",
        "source_site": "https://www.youtube.com/"
      },
      {
        "content": "도아나운서님이 (이름)랑 진짜 나래이션 최고잘했는데요 지금은 완전 나래이션 실패예요 뭐가저리 공감안가게 텐션 떨어뜨리는지완전방송국실망대실망 (이름)랑 도아나운서 진짜 케미가 대박이었는데 소유진과하하 텐션 팍팍 떨어지네요",
        "writer": "UgzY43mxs3kegBHV5Rh4AaABAg",
        "write_date": "2021-01-18",
        "url": "https://www.youtube.com/channel/UCK1sVuXaDvJeNwl9noN5nOA",
        "parent_url": "https://www.youtube.com/watch?v=ZnmqK4NPIro",
        "source_site": "https://www.youtube.com/"
      },
      {
        "content": "하영이 입이예뻐서 말바름이 어쩜고렇게예블까 하영이땜 할머니가 일을못하겠다",
        "writer": "UgwriCFK1wKeANclG4B4AaABAg",
        "write_date": "2021-01-18",
        "url": "https://www.youtube.com/channel/UCK1sVuXaDvJeNwl9noN5nOA",
        "parent_url": "https://www.youtube.com/watch?v=ZnmqK4NPIro",
        "source_site": "https://www.youtube.com/"
      },
      {
        "content": "하영이 넘귀여워요 연우오빠 넘 어른스러워요 참 남매가 남달라요매우 부럽습니다,",
        "writer": "UgwWPYisqN6lNqfWMLN4AaABAg",
        "write_date": "2021-01-18",
        "url": "https://www.youtube.com/channel/UCK1sVuXaDvJeNwl9noN5nOA",
        "parent_url": "https://www.youtube.com/watch?v=ZnmqK4NPIro",
        "source_site": "https://www.youtube.com/"
      },
      {
        "content": "울하영이 보면 행복 넘쳐나요 요새 답답하고 지겨운 하루하루 밖에도 마음대로 못나가는데 하영보고 웃고 살아요 행복(반사회적용어) 감사해용 하영귀어위요",
        "writer": "UgxThNQv8CrcebKGd7l4AaABAg",
        "write_date": "2021-01-18",
        "url": "https://www.youtube.com/channel/UCK1sVuXaDvJeNwl9noN5nOA",
        "parent_url": "https://www.youtube.com/watch?v=ZnmqK4NPIro",
        "source_site": "https://www.youtube.com/"
      },
      {
        "content": "아이고 장(이름) 성공했어요 어쩜 저리 착한 아들이부러워요 딸은 똑순이고, 더 더 많이 번창하고 행복하세요",
        "writer": "Ugwv1VKEBR8AOujx0ll4AaABAg",
        "write_date": "2021-01-18",
        "url": "https://www.youtube.com/channel/UCK1sVuXaDvJeNwl9noN5nOA",
        "parent_url": "https://www.youtube.com/watch?v=ZnmqK4NPIro",
        "source_site": "https://www.youtube.com/"
      },
      {
        "content": "하차하면절대안돼요 무슨낙으로살아요",
        "writer": "UgyskPqXeaoN1EsbSAR4AaABAg.9IEgBV6j7ey9IP_hVUXURS",
        "write_date": "2021-01-18",
        "url": "https://www.youtube.com/channel/UCK1sVuXaDvJeNwl9noN5nOA",
        "parent_url": "https://www.youtube.com/watch?v=ZnmqK4NPIro",
        "source_site": "https://www.youtube.com/"
      },
      {
        "content": "아공 힐링 계속 보고싶네여",
        "writer": "UgyskPqXeaoN1EsbSAR4AaABAg.9IEgBV6j7ey9IzBZT6Tz64",
        "write_date": "2021-02-18",
        "url": "https://www.youtube.com/channel/UCK1sVuXaDvJeNwl9noN5nOA",
        "parent_url": "https://www.youtube.com/watch?v=ZnmqK4NPIro",
        "source_site": "https://www.youtube.com/"
      },
      {
        "content": "소유진까지도 괜찮았는데 하하는",
        "writer": "UgzY43mxs3kegBHV5Rh4AaABAg.9ID4ZLvG2of9IFTn5Hgo-T",
        "write_date": "2021-01-18",
        "url": "https://www.youtube.com/channel/UCK1sVuXaDvJeNwl9noN5nOA",
        "parent_url": "https://www.youtube.com/watch?v=ZnmqK4NPIro",
        "source_site": "https://www.youtube.com/"
      },
      {
        "content": "똑순이 정말 똑 떨어져요",
        "writer": "Ugwv1VKEBR8AOujx0ll4AaABAg.9ICfvLKhyaQ9IzBhHSOVP2",
        "write_date": "2021-02-18",
        "url": "https://www.youtube.com/channel/UCK1sVuXaDvJeNwl9noN5nOA",
        "parent_url": "https://www.youtube.com/watch?v=ZnmqK4NPIro",
        "source_site": "https://www.youtube.com/"
      },
      {
        "content": "하영이 연우 사랑스럽고 귀여워요",
        "writer": "Ugw_XA-XGq0ee-kp8J54AaABAg",
        "write_date": "2021-01-18",
        "url": "https://www.youtube.com/channel/UCK1sVuXaDvJeNwl9noN5nOA",
        "parent_url": "https://www.youtube.com/watch?v=ZnmqK4NPIro",
        "source_site": "https://www.youtube.com/"
      },
      {
        "content": "연우가 집에서 아(비속어) 하는 것 보고 동생을 아주 잘 챙기나봐요, 도경환씨 멋져요...",
        "writer": "UgzvUiJDWVni0902rEt4AaABAg",
        "write_date": "2021-01-18",
        "url": "https://www.youtube.com/channel/UCK1sVuXaDvJeNwl9noN5nOA",
        "parent_url": "https://www.youtube.com/watch?v=ZnmqK4NPIro",
        "source_site": "https://www.youtube.com/"
      },
      {
        "content": "너무 이뻐연우. 하영이 도아나운서님 늘 응원합니다.",
        "writer": "Ugw7Re8mub8oyGoT6Qh4AaABAg",
        "write_date": "2021-01-18",
        "url": "https://www.youtube.com/channel/UCK1sVuXaDvJeNwl9noN5nOA",
        "parent_url": "https://www.youtube.com/watch?v=ZnmqK4NPIro",
        "source_site": "https://www.youtube.com/"
      },
      {
        "content": "세상에 연우는 어쩜저리 착하지 동생을 위에서 뭐든지 척척",
        "writer": "UgxzDKCwx6qXrZD5Gox4AaABAg",
        "write_date": "2021-01-18",
        "url": "https://www.youtube.com/channel/UCK1sVuXaDvJeNwl9noN5nOA",
        "parent_url": "https://www.youtube.com/watch?v=ZnmqK4NPIro",
        "source_site": "https://www.youtube.com/"
      },
      {
        "content": "하영이 너무 귀엽다 달콤해 근데 처음이라서 그런지 하하 나레이션 너무 없네요, 도아나운서가 그리워요, 목소리도 그렇고 재미도 그렇고,",
        "writer": "UgxWgUwBoPCOyl8u5UN4AaABAg",
        "write_date": "2021-01-18",
        "url": "https://www.youtube.com/channel/UCK1sVuXaDvJeNwl9noN5nOA",
        "parent_url": "https://www.youtube.com/watch?v=ZnmqK4NPIro",
        "source_site": "https://www.youtube.com/"
      },
      {
        "content": "하영이 좋겠다 오(비속어) 잘해줘서",
        "writer": "UgwLi4tq0HwNcr8LTu54AaABAg",
        "write_date": "2021-01-18",
        "url": "https://www.youtube.com/channel/UCK1sVuXaDvJeNwl9noN5nOA",
        "parent_url": "https://www.youtube.com/watch?v=ZnmqK4NPIro",
        "source_site": "https://www.youtube.com/"
      },
      {
        "content": "맛있게 먹으세요, Enjoy your home made mandoo.",
        "writer": "UgwgYaRukxJT6OA69-V4AaABAg",
        "write_date": "2021-01-18",
        "url": "https://www.youtube.com/channel/UCK1sVuXaDvJeNwl9noN5nOA",
        "parent_url": "https://www.youtube.com/watch?v=ZnmqK4NPIro",
        "source_site": "https://www.youtube.com/"
      },
      {
        "content": "하영이 넘예쁘요 귀여워죽겠어요 하영보는재미가넘쳐요",
        "writer": "Ugwj3HL4nAI9-bJ6th94AaABAg.9ICWPba3d4J9IGcB3t6ql0",
        "write_date": "2021-01-18",
        "url": "https://www.youtube.com/channel/UCK1sVuXaDvJeNwl9noN5nOA",
        "parent_url": "https://www.youtube.com/watch?v=ZnmqK4NPIro",
        "source_site": "https://www.youtube.com/"
      },
      {
        "content": "저도 이 가족 왕팬인데요. 죄송하지만 도경환이 아니라 도경완 님입니다. 많은 분들이 잘못 알고 계셔서 알려드려요.",
        "writer": "UgzV4wRwfKI_TLCv1T94AaABAg.9ICEzEGJ4SJ9IGy3GzZ7Ls",
        "write_date": "2021-01-18",
        "url": "https://www.youtube.com/channel/UCK1sVuXaDvJeNwl9noN5nOA",
        "parent_url": "https://www.youtube.com/watch?v=ZnmqK4NPIro",
        "source_site": "https://www.youtube.com/"
      },
      {
        "content": "도하영 보는재미로 유트브 보는데 어쩜좋아요",
        "writer": "UgxzDKCwx6qXrZD5Gox4AaABAg.9IBmeMXlWIs9L5cGyWh2h-",
        "write_date": "2021-04-18",
        "url": "https://www.youtube.com/channel/UCK1sVuXaDvJeNwl9noN5nOA",
        "parent_url": "https://www.youtube.com/watch?v=ZnmqK4NPIro",
        "source_site": "https://www.youtube.com/"
      },
      {
        "content": "나래이션 너무 못하네요 소유진 짝꿍 바꿔 주세요",
        "writer": "UgxWgUwBoPCOyl8u5UN4AaABAg.9IBlcQTFn9y9IIEIlXB3Di",
        "write_date": "2021-01-18",
        "url": "https://www.youtube.com/channel/UCK1sVuXaDvJeNwl9noN5nOA",
        "parent_url": "https://www.youtube.com/watch?v=ZnmqK4NPIro",
        "source_site": "https://www.youtube.com/"
      },
      {
        "content": "맞아요 하하 그냥 웃거나 귀엽다는 말만 하고, 나레이션을 너무못해요,",
        "writer": "UgxWgUwBoPCOyl8u5UN4AaABAg.9IBlcQTFn9y9IJgiWbeB8c",
        "write_date": "2021-01-18",
        "url": "https://www.youtube.com/channel/UCK1sVuXaDvJeNwl9noN5nOA",
        "parent_url": "https://www.youtube.com/watch?v=ZnmqK4NPIro",
        "source_site": "https://www.youtube.com/"
      },
      {
        "content": "하하 나레이션 진짜 무성의하고 차라리 안하는 게 나을 듯",
        "writer": "UgxWgUwBoPCOyl8u5UN4AaABAg.9IBlcQTFn9y9IeHT2le_Ny",
        "write_date": "2021-02-18",
        "url": "https://www.youtube.com/channel/UCK1sVuXaDvJeNwl9noN5nOA",
        "parent_url": "https://www.youtube.com/watch?v=ZnmqK4NPIro",
        "source_site": "https://www.youtube.com/"
      },
      {
        "content": "도책 바가지 진짜 그리워요. 하하 나레이션 정말 못한다. 차라리 없는게 더 나아요",
        "writer": "UgxWgUwBoPCOyl8u5UN4AaABAg.9IBlcQTFn9y9K3TvIN_iKJ",
        "write_date": "2021-03-18",
        "url": "https://www.youtube.com/channel/UCK1sVuXaDvJeNwl9noN5nOA",
        "parent_url": "https://www.youtube.com/watch?v=ZnmqK4NPIro",
        "source_site": "https://www.youtube.com/"
      },
      {
        "content": "도경완 아나운서 KBS 사표내도 슈돌에 하영이하고 연우 계속해서 나오게 해주세요 하영이와 연우 땡순에 슈돌 봅니다 왕팬입니다",
        "writer": "UgwLi4tq0HwNcr8LTu54AaABAg.9I6bP6bTEsM9II9oJ8hV7M",
        "write_date": "2021-01-18",
        "url": "https://www.youtube.com/channel/UCK1sVuXaDvJeNwl9noN5nOA",
        "parent_url": "https://www.youtube.com/watch?v=ZnmqK4NPIro",
        "source_site": "https://www.youtube.com/"
      },
      {
        "content": "옳소 ...",
        "writer": "Ugx1mQ13w99KpleGZBt4AaABAg.9I2wvLvmBSi9KtpxW-l8mQ",
        "write_date": "2021-03-18",
        "url": "https://www.youtube.com/channel/UCK1sVuXaDvJeNwl9noN5nOA",
        "parent_url": "https://www.youtube.com/watch?v=ZnmqK4NPIro",
        "source_site": "https://www.youtube.com/"
      }
    ]
  }
}