{
  "SJML": {
    "header": {
      "identifier": "텍스트_구어체 말뭉치 구축_0001651738",
      "name": "컨테이너 텍스트 인식을 위한 학습용 데이터셋",
      "type": "0",
      "source_file": "BOBR210001651738"
    },
    "text": [
      {
        "content": "(비속어) 찌질한놈. 맞더(반사회적용어) 싸워야지 무릎은 왜꿀어. 그리고 꿀엇으면 끝이지 왜 신고하고 방송국에 보도를하냐.",
        "writer": "Ugxw-nT4mBtE-nhylm14AaABAg",
        "write_date": "2021-10-15",
        "url": "https://www.youtube.com/channel/UCHlSeJxRIXZWMARC2oMwmcQ",
        "parent_url": "https://www.youtube.com/watch?v=S1V-EHvxQlc",
        "source_site": "https://www.youtube.com/"
      },
      {
        "content": "(이름)수홍 뽑아서 (비속어)들 전부 사형(반사회적용어)자 ..............",
        "writer": "UgwUtjjWonlH5fzAueN4AaABAg",
        "write_date": "2021-10-15",
        "url": "https://www.youtube.com/channel/UCHlSeJxRIXZWMARC2oMwmcQ",
        "parent_url": "https://www.youtube.com/watch?v=S1V-EHvxQlc",
        "source_site": "https://www.youtube.com/"
      },
      {
        "content": "여럿이서 치사하게 한사람을 공격하냐 저건 특수폭행 가중처벌 현실은 솜방망이",
        "writer": "UgznLgmhvyNbpHYyLFh4AaABAg",
        "write_date": "2021-10-15",
        "url": "https://www.youtube.com/channel/UCHlSeJxRIXZWMARC2oMwmcQ",
        "parent_url": "https://www.youtube.com/watch?v=S1V-EHvxQlc",
        "source_site": "https://www.youtube.com/"
      },
      {
        "content": "3명이 한명을 떄리면 특수로 들어 갑니다 상처 났으면 특수 상해죄로 들어 갑니다 일반 폭행 보다 훨씬 처벌 쌥니다",
        "writer": "Ugz9eBAK-5H0jA9p6rV4AaABAg",
        "write_date": "2021-10-15",
        "url": "https://www.youtube.com/channel/UCHlSeJxRIXZWMARC2oMwmcQ",
        "parent_url": "https://www.youtube.com/watch?v=S1V-EHvxQlc",
        "source_site": "https://www.youtube.com/"
      },
      {
        "content": "합의 하지말고 (반사회적용어)에 집어 넣읍시다",
        "writer": "Ugx-Q5HLg9cMiNpyNd14AaABAg",
        "write_date": "2021-10-15",
        "url": "https://www.youtube.com/channel/UCHlSeJxRIXZWMARC2oMwmcQ",
        "parent_url": "https://www.youtube.com/watch?v=S1V-EHvxQlc",
        "source_site": "https://www.youtube.com/"
      },
      {
        "content": "(비속어)같은(비속어)들이네요 강하게처벌해주세요",
        "writer": "UgwC38fNbIZiv0I2xAl4AaABAg",
        "write_date": "2021-10-15",
        "url": "https://www.youtube.com/channel/UCHlSeJxRIXZWMARC2oMwmcQ",
        "parent_url": "https://www.youtube.com/watch?v=S1V-EHvxQlc",
        "source_site": "https://www.youtube.com/"
      },
      {
        "content": "(혐오표현)미수 인간들",
        "writer": "UgwBVwdEGNvUsSRU5JN4AaABAg",
        "write_date": "2021-10-15",
        "url": "https://www.youtube.com/channel/UCHlSeJxRIXZWMARC2oMwmcQ",
        "parent_url": "https://www.youtube.com/watch?v=S1V-EHvxQlc",
        "source_site": "https://www.youtube.com/"
      },
      {
        "content": "저넘들 눈알을 뽑아버려라",
        "writer": "UgxIbPhujTwb7s_caVx4AaABAg",
        "write_date": "2021-10-15",
        "url": "https://www.youtube.com/channel/UCHlSeJxRIXZWMARC2oMwmcQ",
        "parent_url": "https://www.youtube.com/watch?v=S1V-EHvxQlc",
        "source_site": "https://www.youtube.com/"
      },
      {
        "content": "일대일 이면 쪽도 못쓰는것들이 꼭 쪽수믿고 깝죽대는 (비속어)들.",
        "writer": "UgxQEeq5zPv43QjkJvl4AaABAg",
        "write_date": "2021-10-15",
        "url": "https://www.youtube.com/channel/UCHlSeJxRIXZWMARC2oMwmcQ",
        "parent_url": "https://www.youtube.com/watch?v=S1V-EHvxQlc",
        "source_site": "https://www.youtube.com/"
      },
      {
        "content": "세상이 어떻해서 이지경까지 왔는지, 앞으로 사람처다보지말고 땅만봐야 할듯,",
        "writer": "UgyoePuT-0WTOop5L-p4AaABAg",
        "write_date": "2021-10-15",
        "url": "https://www.youtube.com/channel/UCHlSeJxRIXZWMARC2oMwmcQ",
        "parent_url": "https://www.youtube.com/watch?v=S1V-EHvxQlc",
        "source_site": "https://www.youtube.com/"
      },
      {
        "content": "술마셨다 해도 그냥 저러면 태형을 줘야한다",
        "writer": "Ugwkf-KKLcdxrSd-2lF4AaABAg",
        "write_date": "2021-10-15",
        "url": "https://www.youtube.com/channel/UCHlSeJxRIXZWMARC2oMwmcQ",
        "parent_url": "https://www.youtube.com/watch?v=S1V-EHvxQlc",
        "source_site": "https://www.youtube.com/"
      },
      {
        "content": "(이름)게 조폭이랑 마주치면 기분이 안 나쁘겠지",
        "writer": "UgzCtHOydSTTcz4-v654AaABAg",
        "write_date": "2021-10-15",
        "url": "https://www.youtube.com/channel/UCHlSeJxRIXZWMARC2oMwmcQ",
        "parent_url": "https://www.youtube.com/watch?v=S1V-EHvxQlc",
        "source_site": "https://www.youtube.com/"
      },
      {
        "content": "저런(비속어)들은싹다잡아서 사형시켜라",
        "writer": "UgyusaVeVCgFUsqdCaB4AaABAg",
        "write_date": "2021-10-15",
        "url": "https://www.youtube.com/channel/UCHlSeJxRIXZWMARC2oMwmcQ",
        "parent_url": "https://www.youtube.com/watch?v=S1V-EHvxQlc",
        "source_site": "https://www.youtube.com/"
      },
      {
        "content": "이딴거 (비속어) 때려라 법강력히해야 정신차림",
        "writer": "Ugx-RiVbGE95X2uIDkN4AaABAg",
        "write_date": "2021-10-15",
        "url": "https://www.youtube.com/channel/UCHlSeJxRIXZWMARC2oMwmcQ",
        "parent_url": "https://www.youtube.com/watch?v=S1V-EHvxQlc",
        "source_site": "https://www.youtube.com/"
      },
      {
        "content": "눈도 뜨고 다니지 말란건가 똑같이 당해봐야한다.",
        "writer": "UgwxZdIoXEv6-6eXapN4AaABAg",
        "write_date": "2021-10-15",
        "url": "https://www.youtube.com/channel/UCHlSeJxRIXZWMARC2oMwmcQ",
        "parent_url": "https://www.youtube.com/watch?v=S1V-EHvxQlc",
        "source_site": "https://www.youtube.com/"
      },
      {
        "content": "혼자서 말하기 너무힘듭니다 제발좀 퍼뜨려주세요 삼청교육대 부활 (반사회적용어)도 실행 소년법폐지 강력한 법 개편 말도안되는 경제논리 여야 싸우지말고 앞의 공약이 이번 대선의 향방을 바꿀것입니다 생명보다 소중한건 없잖아요",
        "writer": "UgxuGd--dy0Gt098kGJ4AaABAg",
        "write_date": "2021-10-15",
        "url": "https://www.youtube.com/channel/UCHlSeJxRIXZWMARC2oMwmcQ",
        "parent_url": "https://www.youtube.com/watch?v=S1V-EHvxQlc",
        "source_site": "https://www.youtube.com/"
      },
      {
        "content": "저런(비속어) 3명잡아서 삽으로 목을 쳐 죽여라",
        "writer": "Ugz8xQhekJntSsSYEUB4AaABAg",
        "write_date": "2021-10-15",
        "url": "https://www.youtube.com/channel/UCHlSeJxRIXZWMARC2oMwmcQ",
        "parent_url": "https://www.youtube.com/watch?v=S1V-EHvxQlc",
        "source_site": "https://www.youtube.com/"
      },
      {
        "content": "떼로 몰려다니면 (비속어) (비속어)들,",
        "writer": "UgwGk7QxtlAw0FuDSvJ4AaABAg",
        "write_date": "2021-10-15",
        "url": "https://www.youtube.com/channel/UCHlSeJxRIXZWMARC2oMwmcQ",
        "parent_url": "https://www.youtube.com/watch?v=S1V-EHvxQlc",
        "source_site": "https://www.youtube.com/"
      },
      {
        "content": "세상이 점점 흉폭해진다. 살기 좋은 세상은 커녕 거꾸로 심해지네",
        "writer": "UgxVvk-ReBup4_52YIF4AaABAg",
        "write_date": "2021-10-15",
        "url": "https://www.youtube.com/channel/UCHlSeJxRIXZWMARC2oMwmcQ",
        "parent_url": "https://www.youtube.com/watch?v=S1V-EHvxQlc",
        "source_site": "https://www.youtube.com/"
      },
      {
        "content": "삼청교육대 반대 미쳤냐",
        "writer": "UgxuGd--dy0Gt098kGJ4AaABAg.9SqAEAmj-lU9SsDWXZ4fjo",
        "write_date": "2021-10-15",
        "url": "https://www.youtube.com/channel/UCHlSeJxRIXZWMARC2oMwmcQ",
        "parent_url": "https://www.youtube.com/watch?v=S1V-EHvxQlc",
        "source_site": "https://www.youtube.com/"
      },
      {
        "content": "아카링 옛날처럼 그런 삼청교육대를 생각하시는건 아니시죠 근데 왜반말이시죠 김(이름)네",
        "writer": "UgxuGd--dy0Gt098kGJ4AaABAg.9SqAEAmj-lU9SsIrx8kxxG",
        "write_date": "2021-10-15",
        "url": "https://www.youtube.com/channel/UCHlSeJxRIXZWMARC2oMwmcQ",
        "parent_url": "https://www.youtube.com/watch?v=S1V-EHvxQlc",
        "source_site": "https://www.youtube.com/"
      },
      {
        "content": "술개(비속어) 뚜까패고 용돈받아도 훈방인 (이름) 나라 (반사회적용어) 기억안나",
        "writer": "UgyE5ByEuln7EOQXIGp4AaABAg",
        "write_date": "2021-10-15",
        "url": "https://www.youtube.com/channel/UCHlSeJxRIXZWMARC2oMwmcQ",
        "parent_url": "https://www.youtube.com/watch?v=S1V-EHvxQlc",
        "source_site": "https://www.youtube.com/"
      },
      {
        "content": "그래서 이(비속어) 어케됐어요 .구속이답인데",
        "writer": "UgxgSchqH7gAa6i1FA54AaABAg",
        "write_date": "2021-10-15",
        "url": "https://www.youtube.com/channel/UCHlSeJxRIXZWMARC2oMwmcQ",
        "parent_url": "https://www.youtube.com/watch?v=S1V-EHvxQlc",
        "source_site": "https://www.youtube.com/"
      },
      {
        "content": "술먹으면 가중처벌하랏 오히려 봐주는건 더 나쁘지",
        "writer": "UgxQUIn2vj-JA0vXu6p4AaABAg",
        "write_date": "2021-10-15",
        "url": "https://www.youtube.com/channel/UCHlSeJxRIXZWMARC2oMwmcQ",
        "parent_url": "https://www.youtube.com/watch?v=S1V-EHvxQlc",
        "source_site": "https://www.youtube.com/"
      },
      {
        "content": "내가 사는 시흥에 저런 사건들이 많아 그리고 엉뚱한 사람한테 왜 화풀이야..",
        "writer": "UgwXbJ7cTU79M-3gHNB4AaABAg",
        "write_date": "2021-10-15",
        "url": "https://www.youtube.com/channel/UCHlSeJxRIXZWMARC2oMwmcQ",
        "parent_url": "https://www.youtube.com/watch?v=S1V-EHvxQlc",
        "source_site": "https://www.youtube.com/"
      },
      {
        "content": "재발방(반사회적용어)위해 눈알을없애는처벌을 해주셔씀합니다만.",
        "writer": "Ugyr90v-LwTiAV40FUR4AaABAg",
        "write_date": "2021-10-15",
        "url": "https://www.youtube.com/channel/UCHlSeJxRIXZWMARC2oMwmcQ",
        "parent_url": "https://www.youtube.com/watch?v=S1V-EHvxQlc",
        "source_site": "https://www.youtube.com/"
      },
      {
        "content": "장씨 아들덕에 전국적으로 유행템이 되었구만유",
        "writer": "UgxKiXDe3Lnnev95r4F4AaABAg",
        "write_date": "2021-10-15",
        "url": "https://www.youtube.com/channel/UCHlSeJxRIXZWMARC2oMwmcQ",
        "parent_url": "https://www.youtube.com/watch?v=S1V-EHvxQlc",
        "source_site": "https://www.youtube.com/"
      },
      {
        "content": "법원 술이 죄 사람은죄없다 없다 없다 난몰라 ,반생하고 있어 집행유예2년 탕. 탕 이겠 우리에 현실이다",
        "writer": "Ugwxn2pvPNrBaj78-Vt4AaABAg",
        "write_date": "2021-10-15",
        "url": "https://www.youtube.com/channel/UCHlSeJxRIXZWMARC2oMwmcQ",
        "parent_url": "https://www.youtube.com/watch?v=S1V-EHvxQlc",
        "source_site": "https://www.youtube.com/"
      },
      {
        "content": "힘 없는사람 한데 겁주지 마세요 (비속어) 도 아니고 진짜욕 나올라카네 휴",
        "writer": "UgysXbAE95fZ0jrU5yd4AaABAg",
        "write_date": "2021-10-15",
        "url": "https://www.youtube.com/channel/UCHlSeJxRIXZWMARC2oMwmcQ",
        "parent_url": "https://www.youtube.com/watch?v=S1V-EHvxQlc",
        "source_site": "https://www.youtube.com/"
      },
      {
        "content": "술이 취해서 그랬다면 가중처벌해야지, 술취해서 그랬다고 한편 봐주고 들어가는 우리내 공권력의 더러운 풍습,",
        "writer": "UgxmKaMSotaRiBUTuAx4AaABAg",
        "write_date": "2021-10-15",
        "url": "https://www.youtube.com/channel/UCHlSeJxRIXZWMARC2oMwmcQ",
        "parent_url": "https://www.youtube.com/watch?v=S1V-EHvxQlc",
        "source_site": "https://www.youtube.com/"
      },
      {
        "content": "학교 가자",
        "writer": "Ugz74cLJX3gKVPt36814AaABAg",
        "write_date": "2021-10-15",
        "url": "https://www.youtube.com/channel/UCHlSeJxRIXZWMARC2oMwmcQ",
        "parent_url": "https://www.youtube.com/watch?v=S1V-EHvxQlc",
        "source_site": "https://www.youtube.com/"
      },
      {
        "content": "저(비속어)들 조폭이네, 몰려다니면서 (반사회적용어)짓하는,주변에 언제도와달라냐 ..벌써 디지게맞는데,말같지도않는,",
        "writer": "Ugx7_ygkN8yYy6UWEOF4AaABAg",
        "write_date": "2021-10-15",
        "url": "https://www.youtube.com/channel/UCHlSeJxRIXZWMARC2oMwmcQ",
        "parent_url": "https://www.youtube.com/watch?v=S1V-EHvxQlc",
        "source_site": "https://www.youtube.com/"
      },
      {
        "content": "얼마나 무서우셨을까. 저것들 싹다 집어넣고 벌좀 제대로 받았음",
        "writer": "UgwuLJJWl7K9qhsHexJ4AaABAg",
        "write_date": "2021-10-15",
        "url": "https://www.youtube.com/channel/UCHlSeJxRIXZWMARC2oMwmcQ",
        "parent_url": "https://www.youtube.com/watch?v=S1V-EHvxQlc",
        "source_site": "https://www.youtube.com/"
      },
      {
        "content": "눈이마주치기싫으면 지(비속어) (비속어)을 바닥에 깔고다니면 되지 (비속어)(비속어)아.... 썬글이 끼고 다녀야겠네,",
        "writer": "UgyDHjXS31BR19Xr20N4AaABAg",
        "write_date": "2021-10-15",
        "url": "https://www.youtube.com/channel/UCHlSeJxRIXZWMARC2oMwmcQ",
        "parent_url": "https://www.youtube.com/watch?v=S1V-EHvxQlc",
        "source_site": "https://www.youtube.com/"
      },
      {
        "content": "술이좀 취하고 기분이좀 나쁘면 집단으로 때려되덜까 절대 봐주지마셔요",
        "writer": "UgwTRD6bv1eR9bc07tl4AaABAg",
        "write_date": "2021-10-15",
        "url": "https://www.youtube.com/channel/UCHlSeJxRIXZWMARC2oMwmcQ",
        "parent_url": "https://www.youtube.com/watch?v=S1V-EHvxQlc",
        "source_site": "https://www.youtube.com/"
      },
      {
        "content": "인간 (비속어)네 (반사회적용어)들은 대체 모하는 건지 제발 처벌좀 강력하게 해야함",
        "writer": "UgxlK1_fSqCTeKdh2p14AaABAg",
        "write_date": "2021-10-15",
        "url": "https://www.youtube.com/channel/UCHlSeJxRIXZWMARC2oMwmcQ",
        "parent_url": "https://www.youtube.com/watch?v=S1V-EHvxQlc",
        "source_site": "https://www.youtube.com/"
      },
      {
        "content": "다 쳐넣어야지",
        "writer": "UgxgGB8T4askSgTHm-94AaABAg",
        "write_date": "2021-10-15",
        "url": "https://www.youtube.com/channel/UCHlSeJxRIXZWMARC2oMwmcQ",
        "parent_url": "https://www.youtube.com/watch?v=S1V-EHvxQlc",
        "source_site": "https://www.youtube.com/"
      },
      {
        "content": "몰려 다니면서 힘 없는 사람 괴롭히는 (비속어)들 진짜 모양 빠지는 인간들이네요",
        "writer": "UgyaIiBexMMbsHqFBOp4AaABAg",
        "write_date": "2021-10-15",
        "url": "https://www.youtube.com/channel/UCHlSeJxRIXZWMARC2oMwmcQ",
        "parent_url": "https://www.youtube.com/watch?v=S1V-EHvxQlc",
        "source_site": "https://www.youtube.com/"
      },
      {
        "content": "처벌이 필요해 큰 처벌이",
        "writer": "UgwaIL_YT39hQmbE7mh4AaABAg",
        "write_date": "2021-10-15",
        "url": "https://www.youtube.com/channel/UCHlSeJxRIXZWMARC2oMwmcQ",
        "parent_url": "https://www.youtube.com/watch?v=S1V-EHvxQlc",
        "source_site": "https://www.youtube.com/"
      },
      {
        "content": "저두 시흥살아요 방가워요",
        "writer": "UgwXbJ7cTU79M-3gHNB4AaABAg.9SpxNlH554Z9Sq2L4flT-g",
        "write_date": "2021-10-15",
        "url": "https://www.youtube.com/channel/UCHlSeJxRIXZWMARC2oMwmcQ",
        "parent_url": "https://www.youtube.com/watch?v=S1V-EHvxQlc",
        "source_site": "https://www.youtube.com/"
      },
      {
        "content": "그쪽이 남의 한말이 기분나쁘면 자신의 귀를 없앨겁니까 남일은 쉽게말하지",
        "writer": "Ugyr90v-LwTiAV40FUR4AaABAg.9Spv92jSiSA9Svk_DAAq_J",
        "write_date": "2021-10-15",
        "url": "https://www.youtube.com/channel/UCHlSeJxRIXZWMARC2oMwmcQ",
        "parent_url": "https://www.youtube.com/watch?v=S1V-EHvxQlc",
        "source_site": "https://www.youtube.com/"
      }
    ]
  }
}