{
  "SJML": {
    "header": {
      "identifier": "텍스트_구어체 말뭉치 구축_0001663975",
      "name": "컨테이너 텍스트 인식을 위한 학습용 데이터셋",
      "type": "0",
      "source_file": "BOBR210001663975"
    },
    "text": [
      {
        "content": "이걸 어트게 되치지, (이름)네",
        "writer": "Ugwn-zumZvymbvIICt94AaABAg",
        "write_date": "2021-05-18",
        "url": "https://www.youtube.com/channel/UCK1sVuXaDvJeNwl9noN5nOA",
        "parent_url": "https://www.youtube.com/watch?v=UdAV3EDA6Eg",
        "source_site": "https://www.youtube.com/"
      },
      {
        "content": "레전드, 기술의 기술을 써버리는 그는, 도덕책",
        "writer": "UgxU9hOQV0CKVksQNEt4AaABAg",
        "write_date": "2021-02-18",
        "url": "https://www.youtube.com/channel/UCK1sVuXaDvJeNwl9noN5nOA",
        "parent_url": "https://www.youtube.com/watch?v=UdAV3EDA6Eg",
        "source_site": "https://www.youtube.com/"
      },
      {
        "content": "(이름) 선수 너무 잘했어요..준우승(이름)...",
        "writer": "UgyZsGu4itafTRwH12d4AaABAg",
        "write_date": "2020-12-18",
        "url": "https://www.youtube.com/channel/UCK1sVuXaDvJeNwl9noN5nOA",
        "parent_url": "https://www.youtube.com/watch?v=UdAV3EDA6Eg",
        "source_site": "https://www.youtube.com/"
      },
      {
        "content": "제목이 스포네",
        "writer": "Ugx9pbohRFXRgAXE1Td4AaABAg",
        "write_date": "2020-11-18",
        "url": "https://www.youtube.com/channel/UCK1sVuXaDvJeNwl9noN5nOA",
        "parent_url": "https://www.youtube.com/watch?v=UdAV3EDA6Eg",
        "source_site": "https://www.youtube.com/"
      },
      {
        "content": "헬스장에서 운동 좀 하는듯한 등 넓은 연예인같은 사람 좋더라 힘도 저 선수정도 있고 핰 그러고보니 나랑 겁나 안어울리는데 무슨생각으로 말한거임",
        "writer": "UgxQhfcrCkHEnOa4zyZ4AaABAg",
        "write_date": "2020-11-18",
        "url": "https://www.youtube.com/channel/UCK1sVuXaDvJeNwl9noN5nOA",
        "parent_url": "https://www.youtube.com/watch?v=UdAV3EDA6Eg",
        "source_site": "https://www.youtube.com/"
      },
      {
        "content": "(이름)선수 너무 너무 멋져요",
        "writer": "Ugx_xAh5m0(반사회적용어)ylNVTq94AaABAg",
        "write_date": "2020-11-18",
        "url": "https://www.youtube.com/channel/UCK1sVuXaDvJeNwl9noN5nOA",
        "parent_url": "https://www.youtube.com/watch?v=UdAV3EDA6Eg",
        "source_site": "https://www.youtube.com/"
      },
      {
        "content": "그리고 결승은 운 좋은거야",
        "writer": "UgxnTTP8Q7EEBv5Zc-F4AaABAg",
        "write_date": "2020-11-18",
        "url": "https://www.youtube.com/channel/UCK1sVuXaDvJeNwl9noN5nOA",
        "parent_url": "https://www.youtube.com/watch?v=UdAV3EDA6Eg",
        "source_site": "https://www.youtube.com/"
      },
      {
        "content": "걍 발림",
        "writer": "UgwnvUVLdW7Ya07gn1F4AaABAg",
        "write_date": "2020-11-18",
        "url": "https://www.youtube.com/channel/UCK1sVuXaDvJeNwl9noN5nOA",
        "parent_url": "https://www.youtube.com/watch?v=UdAV3EDA6Eg",
        "source_site": "https://www.youtube.com/"
      },
      {
        "content": "(이름) 경",
        "writer": "UgyNbyTY5c0nDxzWhbN4AaABAg",
        "write_date": "2020-11-18",
        "url": "https://www.youtube.com/channel/UCK1sVuXaDvJeNwl9noN5nOA",
        "parent_url": "https://www.youtube.com/watch?v=UdAV3EDA6Eg",
        "source_site": "https://www.youtube.com/"
      },
      {
        "content": "다른 경기도 아니고 결정전 영상에 선수이름을 바꿔놓다니,",
        "writer": "UgwXgJKNWzJ5rx0-fzB4AaABAg",
        "write_date": "2020-11-18",
        "url": "https://www.youtube.com/channel/UCK1sVuXaDvJeNwl9noN5nOA",
        "parent_url": "https://www.youtube.com/watch?v=UdAV3EDA6Eg",
        "source_site": "https://www.youtube.com/"
      },
      {
        "content": "이거 제목에 이름수정 언제하실건지,",
        "writer": "Ugz86_oG53W8S4XpPJt4AaABAg",
        "write_date": "2020-11-18",
        "url": "https://www.youtube.com/channel/UCK1sVuXaDvJeNwl9noN5nOA",
        "parent_url": "https://www.youtube.com/watch?v=UdAV3EDA6Eg",
        "source_site": "https://www.youtube.com/"
      },
      {
        "content": "(이름) 선수 끝까지 잘했는데 너무 아쉽다,",
        "writer": "UgyB5IfuYGY-aM8JO-p4AaABAg",
        "write_date": "2020-11-18",
        "url": "https://www.youtube.com/channel/UCK1sVuXaDvJeNwl9noN5nOA",
        "parent_url": "https://www.youtube.com/watch?v=UdAV3EDA6Eg",
        "source_site": "https://www.youtube.com/"
      },
      {
        "content": "(이름) 예선에선 설렁 설렁 하는듯 보였는데 8강부터는 무섭도록 진지하게 하더라",
        "writer": "UgxZECSP7kIiKmbBgG94AaABAg",
        "write_date": "2020-11-18",
        "url": "https://www.youtube.com/channel/UCK1sVuXaDvJeNwl9noN5nOA",
        "parent_url": "https://www.youtube.com/watch?v=UdAV3EDA6Eg",
        "source_site": "https://www.youtube.com/"
      },
      {
        "content": "봤었던 경기인데 다시 봐도 쫄깃 (이름) 장사 너무 멋져요",
        "writer": "Ugwb61_hSjqXUD8jP5F4AaABAg",
        "write_date": "2020-11-18",
        "url": "https://www.youtube.com/channel/UCK1sVuXaDvJeNwl9noN5nOA",
        "parent_url": "https://www.youtube.com/watch?v=UdAV3EDA6Eg",
        "source_site": "https://www.youtube.com/"
      },
      {
        "content": "제목이 잘 못되었어요 정확히 알고 영상제목 달아야죠",
        "writer": "UgynyEInC3-KwR3ycBZ4AaABAg",
        "write_date": "2020-11-18",
        "url": "https://www.youtube.com/channel/UCK1sVuXaDvJeNwl9noN5nOA",
        "parent_url": "https://www.youtube.com/watch?v=UdAV3EDA6Eg",
        "source_site": "https://www.youtube.com/"
      },
      {
        "content": "지난주까지 토욜 밤 바빴었는데 이번주 한가하네요,",
        "writer": "UgxEE4y7JiJ097Iy6YB4AaABAg",
        "write_date": "2020-11-18",
        "url": "https://www.youtube.com/channel/UCK1sVuXaDvJeNwl9noN5nOA",
        "parent_url": "https://www.youtube.com/watch?v=UdAV3EDA6Eg",
        "source_site": "https://www.youtube.com/"
      },
      {
        "content": "이름 수정 하세요",
        "writer": "Ugyx_RR0tLi7p-OM-VJ4AaABAg",
        "write_date": "2020-11-18",
        "url": "https://www.youtube.com/channel/UCK1sVuXaDvJeNwl9noN5nOA",
        "parent_url": "https://www.youtube.com/watch?v=UdAV3EDA6Eg",
        "source_site": "https://www.youtube.com/"
      },
      {
        "content": "제목에 성함 수(이름)세요",
        "writer": "Ugx52aQ0E-vW0dcjebd4AaABAg",
        "write_date": "2020-11-18",
        "url": "https://www.youtube.com/channel/UCK1sVuXaDvJeNwl9noN5nOA",
        "parent_url": "https://www.youtube.com/watch?v=UdAV3EDA6Eg",
        "source_site": "https://www.youtube.com/"
      },
      {
        "content": "이름이 서로 바뀌었어요.",
        "writer": "UgxLiosrOJmEr2HhlFx4AaABAg",
        "write_date": "2020-11-18",
        "url": "https://www.youtube.com/channel/UCK1sVuXaDvJeNwl9noN5nOA",
        "parent_url": "https://www.youtube.com/watch?v=UdAV3EDA6Eg",
        "source_site": "https://www.youtube.com/"
      },
      {
        "content": "(이름)가 이긴 줄, (이름) 화이팅..",
        "writer": "UgxKyJcMXc-9m2bAD3F4AaABAg",
        "write_date": "2020-11-18",
        "url": "https://www.youtube.com/channel/UCK1sVuXaDvJeNwl9noN5nOA",
        "parent_url": "https://www.youtube.com/watch?v=UdAV3EDA6Eg",
        "source_site": "https://www.youtube.com/"
      },
      {
        "content": "you only 내말이,",
        "writer": "UgxEE4y7JiJ097Iy6YB4AaABAg.95cUzbSpdU7969o-pRoSe_",
        "write_date": "2020-11-18",
        "url": "https://www.youtube.com/channel/UCK1sVuXaDvJeNwl9noN5nOA",
        "parent_url": "https://www.youtube.com/watch?v=UdAV3EDA6Eg",
        "source_site": "https://www.youtube.com/"
      },
      {
        "content": "캬 꿀잼",
        "writer": "UgzNt1jm00_USeeAh154AaABAg",
        "write_date": "2020-11-18",
        "url": "https://www.youtube.com/channel/UCK1sVuXaDvJeNwl9noN5nOA",
        "parent_url": "https://www.youtube.com/watch?v=UdAV3EDA6Eg",
        "source_site": "https://www.youtube.com/"
      },
      {
        "content": "제목 잘못 쓰신거 같은데",
        "writer": "UgxZlH2SvLu9l1vNdex4AaABAg",
        "write_date": "2020-11-18",
        "url": "https://www.youtube.com/channel/UCK1sVuXaDvJeNwl9noN5nOA",
        "parent_url": "https://www.youtube.com/watch?v=UdAV3EDA6Eg",
        "source_site": "https://www.youtube.com/"
      }
    ]
  }
}